Paralelo/ParaleloRX/probador_PSRX.v
module probador_PSRX(input out_serial2_conductual,
								input out_serial2_estructural,
								output reg clk_4f,
								output reg active,
						        output reg clk_32f);
	initial begin
	$dumpfile("paraleloserialrx.vcd");
	$dumpvars;

	active <= 0;
	
	@(posedge clk_4f);
	active <= 0;


	@(posedge clk_4f);
	active <= 1;
	
	@(posedge clk_4f);
	active <= 0;
	

	@(posedge clk_4f);
	active <= 1;
	

	@(posedge clk_4f);
	active <= 0;
	

	@(posedge clk_4f);
	active <= 1;
	

	@(posedge clk_4f);
	active <= 0;
	

	@(posedge clk_4f);
	active <= 1;
	@(posedge clk_4f);
	$finish;
	end
	
	initial clk_4f <= 1;
	always #8 clk_4f <= ~clk_4f;

	initial clk_32f <= 1;
	always #1 clk_32f <= ~clk_32f;


endmodule

Paralelo/ParaleloRX/synth_PSRX.v
/* Generated by Yosys 0.9 (git sha1 1979e0b) */

(* top =  1  *)
(* src = "synth_PSRX.v:1" *)
module synth_PSRX(clk_4f, clk_32f, active, out_serial2_estructural);
  (* src = "synth_PSRX.v:9" *)
  wire _000_;
  (* src = "synth_PSRX.v:9" *)
  wire [2:0] _001_;
  (* src = "synth_PSRX.v:9" *)
  wire [2:0] _002_;
  (* src = "synth_PSRX.v:27" *)
  (* unused_bits = "3" *)
  wire [31:0] _003_;
  (* src = "synth_PSRX.v:44" *)
  (* unused_bits = "3" *)
  wire [31:0] _004_;
  wire _005_;
  wire _006_;
  wire _007_;
  wire _008_;
  wire _009_;
  wire _010_;
  wire _011_;
  wire _012_;
  wire _013_;
  wire _014_;
  wire _015_;
  wire _016_;
  wire _017_;
  wire [1:0] _018_;
  wire _019_;
  wire _020_;
  wire [1:0] _021_;
  wire _022_;
  wire _023_;
  wire _024_;
  wire [2:0] _025_;
  wire [2:0] _026_;
  wire _027_;
  wire _028_;
  wire _029_;
  wire _030_;
  wire _031_;
  wire _032_;
  wire _033_;
  wire _034_;
  wire _035_;
  wire _036_;
  wire _037_;
  wire _038_;
  wire _039_;
  wire _040_;
  wire _041_;
  wire _042_;
  wire _043_;
  wire _044_;
  wire _045_;
  wire _046_;
  wire _047_;
  wire _048_;
  wire _049_;
  wire _050_;
  wire _051_;
  wire _052_;
  wire _053_;
  wire _054_;
  wire _055_;
  wire _056_;
  wire _057_;
  wire _058_;
  (* src = "synth_PSRX.v:27|<techmap.v>:260|<techmap.v>:203" *)
  (* unused_bits = "2" *)
  wire [31:0] _059_;
  (* src = "synth_PSRX.v:44|PSRX.v:27|<techmap.v>:260|<techmap.v>:203" *)
  (* unused_bits = "2" *)
  wire [31:0] _060_;
  (* src = "synth_PSRX.v:22|PSRX.v:14|<techmap.v>:445" *)
  wire _061_;
  (* src = "synth_PSRX.v:39|PSRX.v:31|<techmap.v>:445" *)
  wire _062_;
  (* src = "synth_PSRX.v:3" *)
  input active;
  (* src = "synth_PSRX.v:2" *)
  input clk_32f;
  (* src = "synth_PSRX.v:1" *)
  input clk_4f;
  (* src = "synth_PSRX.v:4" *)
  output out_serial2_estructural;
  reg out_serial2_estructural;
  (* src = "synth_PSRX.v:6" *)
  reg [2:0] selector;
  (* src = "synth_PSRX.v:7" *)
  reg [2:0] selector_2;
  assign _027_ = _009_ |(* src = "synth_PSRX.v:39|PSRX.v:31" *)  _025_[2];
  assign _028_ = _010_ |(* src = "synth_PSRX.v:38|PSRX.v:31" *)  _025_[2];
  assign _029_ = _011_ |(* src = "synth_PSRX.v:37|PSRX.v:31" *)  _025_[2];
  assign _030_ = _012_ |(* src = "synth_PSRX.v:36|PSRX.v:31" *)  _025_[2];
  assign _009_ = _004_[0] |(* src = "synth_PSRX.v:35|PSRX.v:31" *)  _025_[1];
  assign _031_ = _009_ |(* src = "synth_PSRX.v:35|PSRX.v:31" *)  selector[2];
  assign _010_ = selector[0] |(* src = "synth_PSRX.v:34|PSRX.v:31" *)  _025_[1];
  assign _032_ = _010_ |(* src = "synth_PSRX.v:34|PSRX.v:31" *)  selector[2];
  assign _011_ = _004_[0] |(* src = "synth_PSRX.v:33|PSRX.v:31" *)  selector[1];
  assign _033_ = _011_ |(* src = "synth_PSRX.v:33|PSRX.v:31" *)  selector[2];
  assign _013_ = _003_[0] |(* src = "synth_PSRX.v:22|PSRX.v:14" *)  _026_[1];
  assign _034_ = _013_ |(* src = "synth_PSRX.v:22|PSRX.v:14" *)  _026_[2];
  assign _014_ = selector_2[0] |(* src = "synth_PSRX.v:21|PSRX.v:14" *)  _026_[1];
  assign _035_ = _014_ |(* src = "synth_PSRX.v:21|PSRX.v:14" *)  _026_[2];
  assign _015_ = _003_[0] |(* src = "synth_PSRX.v:20|PSRX.v:14" *)  selector_2[1];
  assign _036_ = _015_ |(* src = "synth_PSRX.v:20|PSRX.v:14" *)  _026_[2];
  assign _037_ = _016_ |(* src = "synth_PSRX.v:19|PSRX.v:14" *)  _026_[2];
  assign _038_ = _013_ |(* src = "synth_PSRX.v:18|PSRX.v:14" *)  selector_2[2];
  assign _039_ = _014_ |(* src = "synth_PSRX.v:17|PSRX.v:14" *)  selector_2[2];
  assign _040_ = _015_ |(* src = "synth_PSRX.v:16|PSRX.v:14" *)  selector_2[2];
  assign _017_ = _053_ | _047_;
  assign _005_ = _017_ | _046_;
  assign _018_[0] = _052_ | _051_;
  assign _018_[1] = _050_ | _048_;
  assign _019_ = _018_[0] | _018_[1];
  assign _006_ = _019_ | _049_;
  assign _020_ = _043_ | _055_;
  assign _007_ = _020_ | _056_;
  assign _021_[0] = _044_ | _042_;
  assign _021_[1] = _041_ | _058_;
  assign _022_ = _021_[0] | _021_[1];
  assign _008_ = _022_ | _057_;
  assign _062_ = _007_ |(* src = "synth_PSRX.v:39|PSRX.v:31|<techmap.v>:445" *)  _008_;
  assign _061_ = _005_ |(* src = "synth_PSRX.v:22|PSRX.v:14|<techmap.v>:445" *)  _006_;
  assign _012_ = selector[0] |(* src = "synth_PSRX.v:32|PSRX.v:31" *)  selector[1];
  assign _023_ = _012_ |(* src = "synth_PSRX.v:32|PSRX.v:31" *)  selector[2];
  assign _016_ = selector_2[0] |(* src = "synth_PSRX.v:15|PSRX.v:14" *)  selector_2[1];
  assign _024_ = _016_ |(* src = "synth_PSRX.v:15|PSRX.v:14" *)  selector_2[2];
  assign _055_ = ~(* src = "synth_PSRX.v:39|PSRX.v:31" *) _027_;
  assign _056_ = ~(* src = "synth_PSRX.v:38|PSRX.v:31" *) _028_;
  assign _057_ = ~(* src = "synth_PSRX.v:37|PSRX.v:31" *) _029_;
  assign _058_ = ~(* src = "synth_PSRX.v:36|PSRX.v:31" *) _030_;
  assign _041_ = ~(* src = "synth_PSRX.v:35|PSRX.v:31" *) _031_;
  assign _042_ = ~(* src = "synth_PSRX.v:34|PSRX.v:31" *) _032_;
  assign _043_ = ~(* src = "synth_PSRX.v:33|PSRX.v:31" *) _033_;
  assign _044_ = ~(* src = "synth_PSRX.v:32|PSRX.v:31" *) _023_;
  assign _046_ = ~(* src = "synth_PSRX.v:22|PSRX.v:14" *) _034_;
  assign _047_ = ~(* src = "synth_PSRX.v:21|PSRX.v:14" *) _035_;
  assign _048_ = ~(* src = "synth_PSRX.v:20|PSRX.v:14" *) _036_;
  assign _049_ = ~(* src = "synth_PSRX.v:19|PSRX.v:14" *) _037_;
  assign _050_ = ~(* src = "synth_PSRX.v:18|PSRX.v:14" *) _038_;
  assign _051_ = ~(* src = "synth_PSRX.v:17|PSRX.v:14" *) _039_;
  assign _052_ = ~(* src = "synth_PSRX.v:16|PSRX.v:14" *) _040_;
  assign _053_ = ~(* src = "synth_PSRX.v:15|PSRX.v:14" *) _024_;
  assign _000_ = active ? (* src = "synth_PSRX.v:12" *) _045_ : _054_;
  assign _002_[0] = active ? (* src = "synth_PSRX.v:12" *) _003_[0] : 1'h0;
  assign _002_[1] = active ? (* src = "synth_PSRX.v:12" *) _003_[1] : 1'h0;
  assign _002_[2] = active ? (* src = "synth_PSRX.v:12" *) _003_[2] : 1'h0;
  assign _001_[0] = active ? (* src = "synth_PSRX.v:12" *) 1'h0 : _004_[0];
  assign _001_[1] = active ? (* src = "synth_PSRX.v:12" *) 1'h0 : _004_[1];
  assign _001_[2] = active ? (* src = "synth_PSRX.v:12" *) 1'h0 : _004_[2];
  assign _054_ = _062_ ? (* src = "synth_PSRX.v:39|PSRX.v:31|<techmap.v>:445" *) _008_ : 1'hx;
  assign _045_ = _061_ ? (* src = "synth_PSRX.v:22|PSRX.v:14|<techmap.v>:445" *) _006_ : 1'hx;
  (* src = "synth_PSRX.v:9" *)
  always @(posedge clk_32f)
      selector[0] <= _001_[0];
  (* src = "synth_PSRX.v:9" *)
  always @(posedge clk_32f)
      selector[1] <= _001_[1];
  (* src = "synth_PSRX.v:9" *)
  always @(posedge clk_32f)
      selector[2] <= _001_[2];
  (* src = "synth_PSRX.v:9" *)
  always @(posedge clk_32f)
      selector_2[0] <= _002_[0];
  (* src = "synth_PSRX.v:9" *)
  always @(posedge clk_32f)
      selector_2[1] <= _002_[1];
  (* src = "synth_PSRX.v:9" *)
  always @(posedge clk_32f)
      selector_2[2] <= _002_[2];
  (* src = "synth_PSRX.v:9" *)
  always @(posedge clk_32f)
      out_serial2_estructural <= _000_;
  assign _060_[1] = selector[1] &(* src = "synth_PSRX.v:44|PSRX.v:27|<techmap.v>:260|<techmap.v>:221" *)  selector[0];
  assign _025_[2] = selector[2] ^(* src = "synth_PSRX.v:36|PSRX.v:31" *)  1'h1;
  assign _025_[1] = selector[1] ^(* src = "synth_PSRX.v:34|PSRX.v:31" *)  1'h1;
  assign _004_[0] = selector[0] ^(* src = "synth_PSRX.v:33|PSRX.v:31" *)  1'h1;
  assign _026_[2] = selector_2[2] ^(* src = "synth_PSRX.v:19|PSRX.v:14" *)  1'h1;
  assign _026_[1] = selector_2[1] ^(* src = "synth_PSRX.v:17|PSRX.v:14" *)  1'h1;
  assign _003_[0] = selector_2[0] ^(* src = "synth_PSRX.v:16|PSRX.v:14" *)  1'h1;
  assign _003_[1] = selector_2[1] ^(* src = "synth_PSRX.v:27|<techmap.v>:263" *)  selector_2[0];
  assign _003_[2] = selector_2[2] ^(* src = "synth_PSRX.v:27|<techmap.v>:263" *)  _059_[1];
  assign _004_[1] = selector[1] ^(* src = "synth_PSRX.v:44|PSRX.v:27|<techmap.v>:263" *)  selector[0];
  assign _004_[2] = selector[2] ^(* src = "synth_PSRX.v:44|PSRX.v:27|<techmap.v>:263" *)  _060_[1];
  assign _059_[1] = selector_2[1] &(* src = "synth_PSRX.v:27|<techmap.v>:260|<techmap.v>:221" *)  selector_2[0];
  assign _003_[31:4] = 28'h0000000;
  assign _004_[31:4] = 28'h0000000;
  assign _025_[0] = selector[0];
  assign _026_[0] = _003_[0];
  assign { _059_[31:2], _059_[0] } = { 29'h00000000, _003_[3], selector_2[0] };
  assign { _060_[31:2], _060_[0] } = { 29'h00000000, _004_[3], selector[0] };
endmodule

Paralelo/ParaleloRX/PSRX.v
module PSRX(input clk_4f,
                        input clk_32f,
                        input active,
                        output reg out_serial2_conductual );

    reg [2:0] selector;
    reg [2:0] selector_2;

    always @(posedge clk_32f) begin

      
            if(active == 1) begin
                selector <= 0;
                case (selector_2)
                    0: out_serial2_conductual <= 0;
                    1: out_serial2_conductual <= 1;
                    2: out_serial2_conductual <= 1;
                    3: out_serial2_conductual <= 1;
                    4: out_serial2_conductual <= 1;
                    5: out_serial2_conductual <= 1;
                    6: out_serial2_conductual <= 0;
                    7: begin
                       out_serial2_conductual <= 0;
                        selector_2 <= 0;
                    end
                endcase
                selector_2 <= selector_2 + 1;
            end
            else begin
                selector_2 <= 0;
                case (selector)
                    0: out_serial2_conductual <= 1;
                    1:out_serial2_conductual<= 0;
                    2:out_serial2_conductual <= 1;
                    3:out_serial2_conductual <= 1;
                    4:out_serial2_conductual <= 1;
                    5:out_serial2_conductual <= 1;
                    6:out_serial2_conductual<= 0;
                    7: begin
                       out_serial2_conductual <= 0;
                        selector <= 0;
                    end
                endcase
                selector <= selector + 1;
            end        
        
        
    end
    
endmodule

Paralelo/ParaleloRX/banco_PSRX.v
`timescale 1ms/100ps

`include "PSRX.v"
`include "probador_PSRX.v"
`include "synth_PSRX.v"

    module banco_paralelo_serial2;
		wire [7:0] in_serial;
		wire clk_4f, clk_32f, active, out_serial2_conductual,out_serial2_estructural;

		PSRX p_s(/*AUTOINST*/
			 // Outputs
			 .out_serial2_conductual(out_serial2_conductual),
			 // Inputs
			 .clk_4f		(clk_4f),
			 .clk_32f		(clk_32f),
			 .active		(active));

		
		synth_PSRX estructural(/*AUTOINST*/
				       // Outputs
				       .out_serial2_estructural(out_serial2_estructural),
				       // Inputs
				       .active		(active),
				       .clk_32f		(clk_32f),
				       .clk_4f		(clk_4f));	   

		
		probador_PSRX prob_paralelo_serial(/*AUTOINST*/
						   // Outputs
						   .clk_4f		(clk_4f),
						   .active		(active),
						   .clk_32f		(clk_32f),
						   // Inputs
						   .out_serial2_conductual(out_serial2_conductual),
						   .out_serial2_estructural(out_serial2_estructural));

    endmodule

Paralelo/ParaleloRX/paraleloserialrx.vcd
$date
	Tue Jun  1 20:50:35 2021
$end
$version
	Icarus Verilog
$end
$timescale
	100ps
$end
$scope module banco_paralelo_serial2 $end
$var wire 1 ! out_serial2_estructural $end
$var wire 1 " out_serial2_conductual $end
$var wire 1 # clk_4f $end
$var wire 1 $ clk_32f $end
$var wire 1 % active $end
$scope module estructural $end
$var wire 1 & _005_ $end
$var wire 1 ' _006_ $end
$var wire 1 ( _007_ $end
$var wire 1 ) _008_ $end
$var wire 1 * _009_ $end
$var wire 1 + _010_ $end
$var wire 1 , _011_ $end
$var wire 1 - _012_ $end
$var wire 1 . _013_ $end
$var wire 1 / _014_ $end
$var wire 1 0 _015_ $end
$var wire 1 1 _016_ $end
$var wire 1 2 _017_ $end
$var wire 1 3 _019_ $end
$var wire 1 4 _020_ $end
$var wire 1 5 _022_ $end
$var wire 1 6 _023_ $end
$var wire 1 7 _024_ $end
$var wire 1 8 _027_ $end
$var wire 1 9 _028_ $end
$var wire 1 : _029_ $end
$var wire 1 ; _030_ $end
$var wire 1 < _031_ $end
$var wire 1 = _032_ $end
$var wire 1 > _033_ $end
$var wire 1 ? _034_ $end
$var wire 1 @ _035_ $end
$var wire 1 A _036_ $end
$var wire 1 B _037_ $end
$var wire 1 C _038_ $end
$var wire 1 D _039_ $end
$var wire 1 E _040_ $end
$var wire 1 F _041_ $end
$var wire 1 G _042_ $end
$var wire 1 H _043_ $end
$var wire 1 I _044_ $end
$var wire 1 J _046_ $end
$var wire 1 K _047_ $end
$var wire 1 L _048_ $end
$var wire 1 M _049_ $end
$var wire 1 N _050_ $end
$var wire 1 O _051_ $end
$var wire 1 P _052_ $end
$var wire 1 Q _053_ $end
$var wire 1 R _055_ $end
$var wire 1 S _056_ $end
$var wire 1 T _057_ $end
$var wire 1 U _058_ $end
$var wire 1 V _061_ $end
$var wire 1 W _062_ $end
$var wire 1 # clk_4f $end
$var wire 1 $ clk_32f $end
$var wire 1 % active $end
$var wire 32 X _060_ [31:0] $end
$var wire 32 Y _059_ [31:0] $end
$var wire 1 Z _054_ $end
$var wire 1 [ _045_ $end
$var wire 3 \ _026_ [2:0] $end
$var wire 3 ] _025_ [2:0] $end
$var wire 2 ^ _021_ [1:0] $end
$var wire 2 _ _018_ [1:0] $end
$var wire 32 ` _004_ [31:0] $end
$var wire 32 a _003_ [31:0] $end
$var wire 3 b _002_ [2:0] $end
$var wire 3 c _001_ [2:0] $end
$var wire 1 d _000_ $end
$var reg 1 ! out_serial2_estructural $end
$var reg 3 e selector [2:0] $end
$var reg 3 f selector_2 [2:0] $end
$upscope $end
$scope module p_s $end
$var wire 1 # clk_4f $end
$var wire 1 $ clk_32f $end
$var wire 1 % active $end
$var reg 1 " out_serial2_conductual $end
$var reg 3 g selector [2:0] $end
$var reg 3 h selector_2 [2:0] $end
$upscope $end
$scope module prob_paralelo_serial $end
$var wire 1 " out_serial2_conductual $end
$var wire 1 ! out_serial2_estructural $end
$var reg 1 % active $end
$var reg 1 $ clk_32f $end
$var reg 1 # clk_4f $end
$upscope $end
$upscope $end
$enddefinitions $end
#0
$dumpvars
b0 h
bx g
b0 f
bx e
xd
bx c
b0 b
b0z001 a
b0zxxx `
b0 _
bx ^
bx ]
b111 \
0[
xZ
b0z00 Y
b0zxx X
xW
1V
xU
xT
xS
xR
1Q
0P
0O
0N
0M
0L
0K
0J
xI
xH
xG
xF
1E
1D
1C
1B
1A
1@
1?
x>
x=
x<
x;
x:
x9
x8
07
x6
x5
x4
03
12
01
10
1/
1.
x-
x,
x+
x*
x)
x(
0'
1&
0%
1$
1#
x"
x!
$end
#10000000
0$
#20000000
1$
#30000000
0$
#40000000
1$
#50000000
0$
#60000000
1$
#70000000
0$
#80000000
1$
0#
#90000000
0$
#100000000
1$
#110000000
0$
#120000000
1$
#130000000
0$
#140000000
1$
#150000000
0$
#160000000
b0 c
b1 b
0d
1%
1$
1#
#170000000
0$
#180000000
1'
1d
13
1Z
1[
1W
1V
b1 _
1)
0&
1P
15
0(
04
0G
0H
0F
02
0E
0U
0T
0S
0R
1=
1>
1<
0Q
00
b10 b
b1 ^
1;
1:
19
18
1+
1,
1*
17
b110 \
1I
11
b0z010 a
b0z01 Y
06
0-
b0z001 `
b0z00 X
b110 ]
0!
b1 f
b0 e
b1 h
0"
b0 g
1$
#190000000
0$
#200000000
1d
1V
1[
1'
13
1O
b1 _
0D
b11 b
0P
0/
1E
b0z011 a
b0z00 Y
10
b101 \
b10 h
1"
b10 f
1!
1$
#210000000
0$
#220000000
1d
1V
1[
1'
13
1N
b10 _
0C
0O
0.
b100 b
1D
b100 \
1/
b0z100 a
b0z11 Y
b11 f
b11 h
1$
#230000000
0$
#240000000
03
0&
02
0J
0K
0L
1M
1.
b0 _
1?
b101 b
1@
1A
0B
0N
1/
10
01
b0z00 Y
1C
b11 \
b0z101 a
b100 h
b100 f
1$
0#
#250000000
0$
#260000000
13
1d
b10 _
1V
1[
1L
1'
0A
0M
00
b110 b
1B
b10 \
11
b0z110 a
b0z01 Y
b101 f
b101 h
1$
#270000000
0$
#280000000
0d
0[
0'
1&
03
12
1K
b0 _
0@
b111 b
0L
0/
1A
b0z111 a
b0z00 Y
10
b1 \
b110 h
b110 f
1$
#290000000
0$
#300000000
1J
02
0?
0K
0.
b0 b
1@
b0 \
1/
b0z000 a
b0z11 Y
0!
b111 f
b111 h
0"
1$
#310000000
0$
#320000000
0[
0'
03
12
0J
0O
0P
1Q
1.
b0 _
1?
1D
1E
07
0N
1/
10
01
b0z00 Y
1C
b111 \
b0z001 a
b1 c
1d
b0 h
b0 f
0%
1$
1#
#330000000
0$
#340000000
0d
0Z
0)
1(
05
14
1H
b0 ^
0>
0I
0,
b10 c
16
1-
b0z010 `
b0z01 X
b111 ]
1!
b1 e
b1 g
1"
1$
#350000000
0$
#360000000
1)
1d
15
1Z
1W
b1 ^
0(
1G
04
0=
b11 c
0H
0+
1>
b0z011 `
b0z00 X
1,
b100 ]
b10 g
0"
b10 e
0!
1$
#370000000
0$
#380000000
1d
1W
1Z
1)
15
1F
b10 ^
0<
0G
0*
b100 c
1=
1+
b0z100 `
b0z11 X
b101 ]
1!
b11 e
b11 g
1"
1$
#390000000
0$
#400000000
1d
1Z
1)
15
04
0(
0R
0S
0T
1U
1*
b10 ^
18
b101 c
19
1:
0;
0F
1+
1,
0-
b0z00 X
1<
b0z101 `
b10 ]
b100 g
b100 e
1$
0#
#410000000
0$
#420000000
05
1T
b0 ^
0:
0U
0,
b110 c
1;
1-
b0z110 `
b0z01 X
b11 ]
b101 e
b101 g
1$
#430000000
0$
#440000000
0d
1(
1W
0Z
1S
0)
09
b111 c
0T
0+
1:
b0z111 `
b0z00 X
1,
b0 ]
b110 g
b110 e
1$
#450000000
0$
#460000000
0d
0Z
14
1W
1R
1(
08
0S
0*
b0 c
19
1+
b0z000 `
b0z11 X
b1 ]
0!
b111 e
b111 g
0"
1$
#470000000
0$
#480000000
0(
1Z
04
1)
15
0R
0G
0H
1I
1*
b1 ^
18
1=
1>
06
0F
1+
1,
0-
b0z00 X
1<
b0z001 `
b110 ]
b1 b
b0 g
b0 e
1%
1$
1#
#490000000
0$
#500000000
1'
1d
13
1[
1V
b1 _
0&
1P
02
0E
0Q
00
b10 b
17
b110 \
11
b0z010 a
b0z01 Y
b1 f
b1 h
1$
#510000000
0$
#520000000
1d
1V
1[
1'
13
1O
b1 _
0D
b11 b
0P
0/
1E
b0z011 a
b0z00 Y
10
b101 \
b10 h
1"
b10 f
1!
1$
#530000000
0$
#540000000
1d
1V
1[
1'
13
1N
b10 _
0C
0O
0.
b100 b
1D
b100 \
1/
b0z100 a
b0z11 Y
b11 f
b11 h
1$
#550000000
0$
#560000000
03
0&
02
0J
0K
0L
1M
1.
b0 _
1?
b101 b
1@
1A
0B
0N
1/
10
01
b0z00 Y
1C
b11 \
b0z101 a
b100 h
b100 f
1$
0#
#570000000
0$
#580000000
13
1d
b10 _
1V
1[
1L
1'
0A
0M
00
b110 b
1B
b10 \
11
b0z110 a
b0z01 Y
b101 f
b101 h
1$
#590000000
0$
#600000000
0d
0[
0'
1&
03
12
1K
b0 _
0@
b111 b
0L
0/
1A
b0z111 a
b0z00 Y
10
b1 \
b110 h
b110 f
1$
#610000000
0$
#620000000
1J
02
0?
0K
0.
b0 b
1@
b0 \
1/
b0z000 a
b0z11 Y
0!
b111 f
b111 h
0"
1$
#630000000
0$
#640000000
0[
0'
03
12
0J
0O
0P
1Q
1.
b0 _
1?
1D
1E
07
0N
1/
10
01
b0z00 Y
1C
b111 \
b0z001 a
b1 c
1d
b0 h
b0 f
0%
1$
1#
#650000000
0$
#660000000
0d
0Z
0)
1(
05
14
1H
b0 ^
0>
0I
0,
b10 c
16
1-
b0z010 `
b0z01 X
b111 ]
1!
b1 e
b1 g
1"
1$
#670000000
0$
#680000000
1)
1d
15
1Z
1W
b1 ^
0(
1G
04
0=
b11 c
0H
0+
1>
b0z011 `
b0z00 X
1,
b100 ]
b10 g
0"
b10 e
0!
1$
#690000000
0$
#700000000
1d
1W
1Z
1)
15
1F
b10 ^
0<
0G
0*
b100 c
1=
1+
b0z100 `
b0z11 X
b101 ]
1!
b11 e
b11 g
1"
1$
#710000000
0$
#720000000
1d
1Z
1)
15
04
0(
0R
0S
0T
1U
1*
b10 ^
18
b101 c
19
1:
0;
0F
1+
1,
0-
b0z00 X
1<
b0z101 `
b10 ]
b100 g
b100 e
1$
0#
#730000000
0$
#740000000
05
1T
b0 ^
0:
0U
0,
b110 c
1;
1-
b0z110 `
b0z01 X
b11 ]
b101 e
b101 g
1$
#750000000
0$
#760000000
0d
1(
1W
0Z
1S
0)
09
b111 c
0T
0+
1:
b0z111 `
b0z00 X
1,
b0 ]
b110 g
b110 e
1$
#770000000
0$
#780000000
0d
0Z
14
1W
1R
1(
08
0S
0*
b0 c
19
1+
b0z000 `
b0z11 X
b1 ]
0!
b111 e
b111 g
0"
1$
#790000000
0$
#800000000
0(
1Z
04
1)
15
0R
0G
0H
1I
1*
b1 ^
18
1=
1>
06
0F
1+
1,
0-
b0z00 X
1<
b0z001 `
b110 ]
b1 b
b0 g
b0 e
1%
1$
1#
#810000000
0$
#820000000
1'
1d
13
1[
1V
b1 _
0&
1P
02
0E
0Q
00
b10 b
17
b110 \
11
b0z010 a
b0z01 Y
b1 f
b1 h
1$
#830000000
0$
#840000000
1d
1V
1[
1'
13
1O
b1 _
0D
b11 b
0P
0/
1E
b0z011 a
b0z00 Y
10
b101 \
b10 h
1"
b10 f
1!
1$
#850000000
0$
#860000000
1d
1V
1[
1'
13
1N
b10 _
0C
0O
0.
b100 b
1D
b100 \
1/
b0z100 a
b0z11 Y
b11 f
b11 h
1$
#870000000
0$
#880000000
03
0&
02
0J
0K
0L
1M
1.
b0 _
1?
b101 b
1@
1A
0B
0N
1/
10
01
b0z00 Y
1C
b11 \
b0z101 a
b100 h
b100 f
1$
0#
#890000000
0$
#900000000
13
1d
b10 _
1V
1[
1L
1'
0A
0M
00
b110 b
1B
b10 \
11
b0z110 a
b0z01 Y
b101 f
b101 h
1$
#910000000
0$
#920000000
0d
0[
0'
1&
03
12
1K
b0 _
0@
b111 b
0L
0/
1A
b0z111 a
b0z00 Y
10
b1 \
b110 h
b110 f
1$
#930000000
0$
#940000000
1J
02
0?
0K
0.
b0 b
1@
b0 \
1/
b0z000 a
b0z11 Y
0!
b111 f
b111 h
0"
1$
#950000000
0$
#960000000
0[
0'
03
12
0J
0O
0P
1Q
1.
b0 _
1?
1D
1E
07
0N
1/
10
01
b0z00 Y
1C
b111 \
b0z001 a
b1 c
1d
b0 h
b0 f
0%
1$
1#
#970000000
0$
#980000000
0d
0Z
0)
1(
05
14
1H
b0 ^
0>
0I
0,
b10 c
16
1-
b0z010 `
b0z01 X
b111 ]
1!
b1 e
b1 g
1"
1$
#990000000
0$
#1000000000
1)
1d
15
1Z
1W
b1 ^
0(
1G
04
0=
b11 c
0H
0+
1>
b0z011 `
b0z00 X
1,
b100 ]
b10 g
0"
b10 e
0!
1$
#1010000000
0$
#1020000000
1d
1W
1Z
1)
15
1F
b10 ^
0<
0G
0*
b100 c
1=
1+
b0z100 `
b0z11 X
b101 ]
1!
b11 e
b11 g
1"
1$
#1030000000
0$
#1040000000
1d
1Z
1)
15
04
0(
0R
0S
0T
1U
1*
b10 ^
18
b101 c
19
1:
0;
0F
1+
1,
0-
b0z00 X
1<
b0z101 `
b10 ]
b100 g
b100 e
1$
0#
#1050000000
0$
#1060000000
05
1T
b0 ^
0:
0U
0,
b110 c
1;
1-
b0z110 `
b0z01 X
b11 ]
b101 e
b101 g
1$
#1070000000
0$
#1080000000
0d
1(
1W
0Z
1S
0)
09
b111 c
0T
0+
1:
b0z111 `
b0z00 X
1,
b0 ]
b110 g
b110 e
1$
#1090000000
0$
#1100000000
0d
0Z
14
1W
1R
1(
08
0S
0*
b0 c
19
1+
b0z000 `
b0z11 X
b1 ]
0!
b111 e
b111 g
0"
1$
#1110000000
0$
#1120000000
0(
1Z
04
1)
15
0R
0G
0H
1I
1*
b1 ^
18
1=
1>
06
0F
1+
1,
0-
b0z00 X
1<
b0z001 `
b110 ]
b1 b
b0 g
b0 e
1%
1$
1#
#1130000000
0$
#1140000000
1'
1d
13
1[
1V
b1 _
0&
1P
02
0E
0Q
00
b10 b
17
b110 \
11
b0z010 a
b0z01 Y
b1 f
b1 h
1$
#1150000000
0$
#1160000000
1d
1V
1[
1'
13
1O
b1 _
0D
b11 b
0P
0/
1E
b0z011 a
b0z00 Y
10
b101 \
b10 h
1"
b10 f
1!
1$
#1170000000
0$
#1180000000
1d
1V
1[
1'
13
1N
b10 _
0C
0O
0.
b100 b
1D
b100 \
1/
b0z100 a
b0z11 Y
b11 f
b11 h
1$
#1190000000
0$
#1200000000
03
0&
02
0J
0K
0L
1M
1.
b0 _
1?
b101 b
1@
1A
0B
0N
1/
10
01
b0z00 Y
1C
b11 \
b0z101 a
b100 h
b100 f
1$
0#
#1210000000
0$
#1220000000
13
1d
b10 _
1V
1[
1L
1'
0A
0M
00
b110 b
1B
b10 \
11
b0z110 a
b0z01 Y
b101 f
b101 h
1$
#1230000000
0$
#1240000000
0d
0[
0'
1&
03
12
1K
b0 _
0@
b111 b
0L
0/
1A
b0z111 a
b0z00 Y
10
b1 \
b110 h
b110 f
1$
#1250000000
0$
#1260000000
1J
02
0?
0K
0.
b0 b
1@
b0 \
1/
b0z000 a
b0z11 Y
0!
b111 f
b111 h
0"
1$
#1270000000
0$
#1280000000
0d
0[
0'
03
12
0J
0O
0P
1Q
1.
b0 _
1?
b1 b
1D
1E
07
0N
1/
10
01
b0z00 Y
1C
b111 \
b0z001 a
b0 h
b0 f
1$
1#
