Paralelo/probador_paralelo_serial.v
module probador_paralelo_serial(input out_serial_conductual,
								input out_serial_estructural,
								output reg clk_4f,
								output reg reset,
								output reg valid_in,
						        output reg [7:0] in_serial,
						        output reg clk_32f);
	initial begin
	$dumpfile("paraleloserial.vcd");
	$dumpvars;

	{valid_in} <= 0;
	in_serial <= 8'h00;
	reset <=0;
	
	@(posedge clk_4f);
	valid_in <= 0;
	in_serial<= 8'h00;
	reset <= 0;

	@(posedge clk_4f);
	valid_in <= 0;
	in_serial<= 8'hCC;
	reset <=1;
	
	@(posedge clk_4f);
	valid_in <= 1;
	in_serial <= 8'hAB;

	@(posedge clk_4f);
	valid_in <= 1;
	in_serial <= 8'hCA;

	@(posedge clk_4f);
	valid_in <= 1;
	in_serial <= 8'h12;

	@(posedge clk_4f);
	valid_in <= 0;
	in_serial <= 8'hDC;

	@(posedge clk_4f);
	valid_in <= 1;
	in_serial <= 8'hFA;

	@(posedge clk_4f);
	valid_in <= 1;
	in_serial <= 8'h33;
	@(posedge clk_4f);
	$finish;
	end
	
	initial clk_4f <= 1;
	always #8 clk_4f <= ~clk_4f;

	initial clk_32f <= 1;
	always #1 clk_32f <= ~clk_32f;


endmodule

Paralelo/synth_paralelo.v
/* Generated by Yosys 0.9 (git sha1 1979e0b) */

(* top =  1  *)
(* src = "synth_paralelo.v:1" *)
module synth_paralelo(clk_4f, clk_32f, in_serial, valid_in, reset, out_serial_estructural);
  (* src = "synth_paralelo.v:11" *)
  wire _000_;
  (* src = "synth_paralelo.v:11" *)
  wire [2:0] _001_;
  (* src = "synth_paralelo.v:11" *)
  wire [2:0] _002_;
  (* src = "synth_paralelo.v:29" *)
  (* unused_bits = "3" *)
  wire [31:0] _003_;
  (* src = "synth_paralelo.v:46" *)
  (* unused_bits = "3" *)
  wire [31:0] _004_;
  wire _005_;
  wire _006_;
  wire _007_;
  wire _008_;
  wire _009_;
  wire _010_;
  wire _011_;
  wire _012_;
  wire _013_;
  wire _014_;
  wire [1:0] _015_;
  wire _016_;
  wire [3:0] _017_;
  wire [1:0] _018_;
  wire [3:0] _019_;
  wire [1:0] _020_;
  wire _021_;
  wire _022_;
  wire _023_;
  wire [2:0] _024_;
  wire [2:0] _025_;
  wire _026_;
  wire _027_;
  wire _028_;
  wire _029_;
  wire _030_;
  wire _031_;
  wire _032_;
  wire _033_;
  wire _034_;
  wire _035_;
  wire _036_;
  wire _037_;
  wire _038_;
  wire _039_;
  wire _040_;
  wire _041_;
  wire _042_;
  wire _043_;
  wire _044_;
  wire _045_;
  wire _046_;
  wire _047_;
  wire _048_;
  (* src = "synth_paralelo.v:24|paralelo_serial.v:16|<techmap.v>:432" *)
  wire [7:0] _049_;
  (* src = "synth_paralelo.v:24|paralelo_serial.v:16|<techmap.v>:428" *)
  wire _050_;
  wire _051_;
  wire _052_;
  wire _053_;
  wire _054_;
  wire _055_;
  wire _056_;
  wire _057_;
  wire _058_;
  wire _059_;
  wire _060_;
  wire [2:0] _061_;
  wire [2:0] _062_;
  (* src = "synth_paralelo.v:29|<techmap.v>:260|<techmap.v>:203" *)
  (* unused_bits = "2" *)
  wire [31:0] _063_;
  (* src = "synth_paralelo.v:46|paralelo_serial.v:29|<techmap.v>:260|<techmap.v>:203" *)
  (* unused_bits = "2" *)
  wire [31:0] _064_;
  (* src = "synth_paralelo.v:41|paralelo_serial.v:33|<techmap.v>:445" *)
  wire _065_;
  (* src = "synth_paralelo.v:24|paralelo_serial.v:16|<techmap.v>:445" *)
  wire _066_;
  (* src = "synth_paralelo.v:2" *)
  input clk_32f;
  (* src = "synth_paralelo.v:1" *)
  input clk_4f;
  (* src = "synth_paralelo.v:3" *)
  input [7:0] in_serial;
  (* src = "synth_paralelo.v:6" *)
  output out_serial_estructural;
  reg out_serial_estructural;
  (* src = "synth_paralelo.v:5" *)
  input reset;
  (* src = "synth_paralelo.v:8" *)
  reg [2:0] selector;
  (* src = "synth_paralelo.v:9" *)
  reg [2:0] selector_2;
  (* src = "synth_paralelo.v:4" *)
  input valid_in;
  assign _026_ = _007_ |(* src = "synth_paralelo.v:41|paralelo_serial.v:33" *)  _024_[2];
  assign _027_ = _008_ |(* src = "synth_paralelo.v:40|paralelo_serial.v:33" *)  _024_[2];
  assign _028_ = _009_ |(* src = "synth_paralelo.v:39|paralelo_serial.v:33" *)  _024_[2];
  assign _029_ = _010_ |(* src = "synth_paralelo.v:38|paralelo_serial.v:33" *)  _024_[2];
  assign _007_ = _004_[0] |(* src = "synth_paralelo.v:37|paralelo_serial.v:33" *)  _024_[1];
  assign _030_ = _007_ |(* src = "synth_paralelo.v:37|paralelo_serial.v:33" *)  selector[2];
  assign _008_ = selector[0] |(* src = "synth_paralelo.v:36|paralelo_serial.v:33" *)  _024_[1];
  assign _031_ = _008_ |(* src = "synth_paralelo.v:36|paralelo_serial.v:33" *)  selector[2];
  assign _009_ = _004_[0] |(* src = "synth_paralelo.v:35|paralelo_serial.v:33" *)  selector[1];
  assign _032_ = _009_ |(* src = "synth_paralelo.v:35|paralelo_serial.v:33" *)  selector[2];
  assign _033_ = _011_ |(* src = "synth_paralelo.v:24|paralelo_serial.v:16" *)  _025_[2];
  assign _012_ = selector_2[0] |(* src = "synth_paralelo.v:23|paralelo_serial.v:16" *)  _025_[1];
  assign _034_ = _012_ |(* src = "synth_paralelo.v:23|paralelo_serial.v:16" *)  _025_[2];
  assign _013_ = _003_[0] |(* src = "synth_paralelo.v:22|paralelo_serial.v:16" *)  selector_2[1];
  assign _035_ = _013_ |(* src = "synth_paralelo.v:22|paralelo_serial.v:16" *)  _025_[2];
  assign _036_ = _014_ |(* src = "synth_paralelo.v:21|paralelo_serial.v:16" *)  _025_[2];
  assign _011_ = _003_[0] |(* src = "synth_paralelo.v:20|paralelo_serial.v:16" *)  _025_[1];
  assign _037_ = _011_ |(* src = "synth_paralelo.v:20|paralelo_serial.v:16" *)  selector_2[2];
  assign _038_ = _012_ |(* src = "synth_paralelo.v:19|paralelo_serial.v:16" *)  selector_2[2];
  assign _039_ = _013_ |(* src = "synth_paralelo.v:18|paralelo_serial.v:16" *)  selector_2[2];
  assign _015_[0] = _048_ | _046_;
  assign _015_[1] = _045_ | _044_;
  assign _016_ = _015_[0] | _015_[1];
  assign _006_ = _016_ | _043_;
  assign _065_ = _005_ |(* src = "synth_paralelo.v:41|paralelo_serial.v:33|<techmap.v>:445" *)  _006_;
  assign _017_[0] = _049_[0] |(* src = "synth_paralelo.v:24|paralelo_serial.v:16|<techmap.v>:441" *)  _049_[1];
  assign _017_[1] = _049_[2] |(* src = "synth_paralelo.v:24|paralelo_serial.v:16|<techmap.v>:441" *)  _049_[3];
  assign _017_[2] = _049_[4] |(* src = "synth_paralelo.v:24|paralelo_serial.v:16|<techmap.v>:441" *)  _049_[5];
  assign _017_[3] = _049_[6] |(* src = "synth_paralelo.v:24|paralelo_serial.v:16|<techmap.v>:441" *)  _049_[7];
  assign _018_[0] = _017_[0] |(* src = "synth_paralelo.v:24|paralelo_serial.v:16|<techmap.v>:441" *)  _017_[1];
  assign _018_[1] = _017_[2] |(* src = "synth_paralelo.v:24|paralelo_serial.v:16|<techmap.v>:441" *)  _017_[3];
  assign _050_ = _018_[0] |(* src = "synth_paralelo.v:24|paralelo_serial.v:16|<techmap.v>:441" *)  _018_[1];
  assign _019_[0] = _052_ |(* src = "synth_paralelo.v:24|paralelo_serial.v:16|<techmap.v>:445" *)  _053_;
  assign _019_[1] = _054_ |(* src = "synth_paralelo.v:24|paralelo_serial.v:16|<techmap.v>:445" *)  _055_;
  assign _019_[2] = _056_ |(* src = "synth_paralelo.v:24|paralelo_serial.v:16|<techmap.v>:445" *)  _057_;
  assign _019_[3] = _058_ |(* src = "synth_paralelo.v:24|paralelo_serial.v:16|<techmap.v>:445" *)  _059_;
  assign _020_[0] = _019_[0] |(* src = "synth_paralelo.v:24|paralelo_serial.v:16|<techmap.v>:445" *)  _019_[1];
  assign _020_[1] = _019_[2] |(* src = "synth_paralelo.v:24|paralelo_serial.v:16|<techmap.v>:445" *)  _019_[3];
  assign _066_ = _020_[0] |(* src = "synth_paralelo.v:24|paralelo_serial.v:16|<techmap.v>:445" *)  _020_[1];
  assign _021_ = _047_ | _042_;
  assign _005_ = _021_ | _041_;
  assign _010_ = selector[0] |(* src = "synth_paralelo.v:34|paralelo_serial.v:33" *)  selector[1];
  assign _022_ = _010_ |(* src = "synth_paralelo.v:34|paralelo_serial.v:33" *)  selector[2];
  assign _014_ = selector_2[0] |(* src = "synth_paralelo.v:17|paralelo_serial.v:16" *)  selector_2[1];
  assign _023_ = _014_ |(* src = "synth_paralelo.v:17|paralelo_serial.v:16" *)  selector_2[2];
  assign _041_ = ~(* src = "synth_paralelo.v:41|paralelo_serial.v:33" *) _026_;
  assign _042_ = ~(* src = "synth_paralelo.v:40|paralelo_serial.v:33" *) _027_;
  assign _043_ = ~(* src = "synth_paralelo.v:39|paralelo_serial.v:33" *) _028_;
  assign _044_ = ~(* src = "synth_paralelo.v:38|paralelo_serial.v:33" *) _029_;
  assign _045_ = ~(* src = "synth_paralelo.v:37|paralelo_serial.v:33" *) _030_;
  assign _046_ = ~(* src = "synth_paralelo.v:36|paralelo_serial.v:33" *) _031_;
  assign _047_ = ~(* src = "synth_paralelo.v:35|paralelo_serial.v:33" *) _032_;
  assign _048_ = ~(* src = "synth_paralelo.v:34|paralelo_serial.v:33" *) _022_;
  assign _052_ = ~(* src = "synth_paralelo.v:24|paralelo_serial.v:16" *) _033_;
  assign _053_ = ~(* src = "synth_paralelo.v:23|paralelo_serial.v:16" *) _034_;
  assign _054_ = ~(* src = "synth_paralelo.v:22|paralelo_serial.v:16" *) _035_;
  assign _055_ = ~(* src = "synth_paralelo.v:21|paralelo_serial.v:16" *) _036_;
  assign _056_ = ~(* src = "synth_paralelo.v:20|paralelo_serial.v:16" *) _037_;
  assign _057_ = ~(* src = "synth_paralelo.v:19|paralelo_serial.v:16" *) _038_;
  assign _058_ = ~(* src = "synth_paralelo.v:18|paralelo_serial.v:16" *) _039_;
  assign _059_ = ~(* src = "synth_paralelo.v:17|paralelo_serial.v:16" *) _023_;
  assign _001_[0] = reset ? (* src = "synth_paralelo.v:13" *) _062_[0] : 1'h0;
  assign _001_[1] = reset ? (* src = "synth_paralelo.v:13" *) _062_[1] : 1'h0;
  assign _001_[2] = reset ? (* src = "synth_paralelo.v:13" *) _062_[2] : 1'h0;
  assign _060_ = valid_in ? (* src = "synth_paralelo.v:14" *) _051_ : _040_;
  assign _000_ = reset ? (* src = "synth_paralelo.v:13" *) _060_ : 1'h0;
  assign _061_[0] = valid_in ? (* src = "synth_paralelo.v:14" *) _003_[0] : 1'h0;
  assign _061_[1] = valid_in ? (* src = "synth_paralelo.v:14" *) _003_[1] : 1'h0;
  assign _061_[2] = valid_in ? (* src = "synth_paralelo.v:14" *) _003_[2] : 1'h0;
  assign _002_[0] = reset ? (* src = "synth_paralelo.v:13" *) _061_[0] : 1'h0;
  assign _002_[1] = reset ? (* src = "synth_paralelo.v:13" *) _061_[1] : 1'h0;
  assign _002_[2] = reset ? (* src = "synth_paralelo.v:13" *) _061_[2] : 1'h0;
  assign _040_ = _065_ ? (* src = "synth_paralelo.v:41|paralelo_serial.v:33|<techmap.v>:445" *) _006_ : 1'hx;
  assign _051_ = _066_ ? (* src = "synth_paralelo.v:24|paralelo_serial.v:16|<techmap.v>:445" *) _050_ : 1'hx;
  assign _062_[0] = valid_in ? (* src = "synth_paralelo.v:14" *) 1'h0 : _004_[0];
  assign _062_[1] = valid_in ? (* src = "synth_paralelo.v:14" *) 1'h0 : _004_[1];
  assign _062_[2] = valid_in ? (* src = "synth_paralelo.v:14" *) 1'h0 : _004_[2];
  (* src = "synth_paralelo.v:11" *)
  always @(posedge clk_32f)
      selector[0] <= _001_[0];
  (* src = "synth_paralelo.v:11" *)
  always @(posedge clk_32f)
      selector[1] <= _001_[1];
  (* src = "synth_paralelo.v:11" *)
  always @(posedge clk_32f)
      selector[2] <= _001_[2];
  (* src = "synth_paralelo.v:11" *)
  always @(posedge clk_32f)
      selector_2[0] <= _002_[0];
  (* src = "synth_paralelo.v:11" *)
  always @(posedge clk_32f)
      selector_2[1] <= _002_[1];
  (* src = "synth_paralelo.v:11" *)
  always @(posedge clk_32f)
      selector_2[2] <= _002_[2];
  (* src = "synth_paralelo.v:11" *)
  always @(posedge clk_32f)
      out_serial_estructural <= _000_;
  assign _064_[1] = selector[1] &(* src = "synth_paralelo.v:46|paralelo_serial.v:29|<techmap.v>:260|<techmap.v>:221" *)  selector[0];
  assign _024_[2] = selector[2] ^(* src = "synth_paralelo.v:38|paralelo_serial.v:33" *)  1'h1;
  assign _024_[1] = selector[1] ^(* src = "synth_paralelo.v:36|paralelo_serial.v:33" *)  1'h1;
  assign _004_[0] = selector[0] ^(* src = "synth_paralelo.v:35|paralelo_serial.v:33" *)  1'h1;
  assign _025_[2] = selector_2[2] ^(* src = "synth_paralelo.v:21|paralelo_serial.v:16" *)  1'h1;
  assign _025_[1] = selector_2[1] ^(* src = "synth_paralelo.v:19|paralelo_serial.v:16" *)  1'h1;
  assign _003_[0] = selector_2[0] ^(* src = "synth_paralelo.v:18|paralelo_serial.v:16" *)  1'h1;
  assign _049_[4] = in_serial[4] &(* src = "synth_paralelo.v:24|paralelo_serial.v:16|<techmap.v>:434" *)  _056_;
  assign _049_[7] = in_serial[7] &(* src = "synth_paralelo.v:24|paralelo_serial.v:16|<techmap.v>:434" *)  _059_;
  assign _049_[6] = in_serial[6] &(* src = "synth_paralelo.v:24|paralelo_serial.v:16|<techmap.v>:434" *)  _058_;
  assign _049_[5] = in_serial[5] &(* src = "synth_paralelo.v:24|paralelo_serial.v:16|<techmap.v>:434" *)  _057_;
  assign _049_[3] = in_serial[3] &(* src = "synth_paralelo.v:24|paralelo_serial.v:16|<techmap.v>:434" *)  _055_;
  assign _049_[2] = in_serial[2] &(* src = "synth_paralelo.v:24|paralelo_serial.v:16|<techmap.v>:434" *)  _054_;
  assign _049_[1] = in_serial[1] &(* src = "synth_paralelo.v:24|paralelo_serial.v:16|<techmap.v>:434" *)  _053_;
  assign _049_[0] = in_serial[0] &(* src = "synth_paralelo.v:24|paralelo_serial.v:16|<techmap.v>:434" *)  _052_;
  assign _003_[1] = selector_2[1] ^(* src = "synth_paralelo.v:29|<techmap.v>:263" *)  selector_2[0];
  assign _003_[2] = selector_2[2] ^(* src = "synth_paralelo.v:29|<techmap.v>:263" *)  _063_[1];
  assign _004_[1] = selector[1] ^(* src = "synth_paralelo.v:46|paralelo_serial.v:29|<techmap.v>:263" *)  selector[0];
  assign _004_[2] = selector[2] ^(* src = "synth_paralelo.v:46|paralelo_serial.v:29|<techmap.v>:263" *)  _064_[1];
  assign _063_[1] = selector_2[1] &(* src = "synth_paralelo.v:29|<techmap.v>:260|<techmap.v>:221" *)  selector_2[0];
  assign _003_[31:4] = 28'h0000000;
  assign _004_[31:4] = 28'h0000000;
  assign _024_[0] = _004_[0];
  assign _025_[0] = _003_[0];
  assign { _063_[31:2], _063_[0] } = { 29'h00000000, _003_[3], selector_2[0] };
  assign { _064_[31:2], _064_[0] } = { 29'h00000000, _004_[3], selector[0] };
endmodule

Paralelo/paralelo_serial.v
module paralelo_serial(input clk_4f,
                        input clk_32f,
                        input [7:0] in_serial,
                        input valid_in,
                        input reset,
                        output reg out_serial_conductual );

    reg [2:0] selector;
    reg [2:0] selector_2;

    always @(posedge clk_32f) begin

        if (reset == 1) begin
            if(valid_in == 1) begin
                selector <= 0;
                case (selector_2)
                    0: out_serial_conductual <= in_serial[7];
                    1: out_serial_conductual <= in_serial[6];
                    2: out_serial_conductual <= in_serial[5];
                    3: out_serial_conductual <= in_serial[4];
                    4: out_serial_conductual <= in_serial[3];
                    5: out_serial_conductual <= in_serial[2];
                    6: out_serial_conductual <= in_serial[1];
                    7: begin
                       out_serial_conductual <= in_serial[0];
                        selector_2 <= 0;
                    end
                endcase
                selector_2 <= selector_2 + 1;
            end
            else begin
                selector_2 <= 0;
                case (selector)
                    0: out_serial_conductual <= 1;
                    1:out_serial_conductual<= 0;
                    2:out_serial_conductual <= 1;
                    3:out_serial_conductual <= 1;
                    4:out_serial_conductual <= 1;
                    5:out_serial_conductual <= 1;
                    6:out_serial_conductual<= 0;
                    7: begin
                       out_serial_conductual <= 0;
                        selector <= 0;
                    end
                endcase
                selector <= selector + 1;
            end
        end
        
        else begin
            out_serial_conductual <= 0;
            {selector, selector_2} <= 0;
        end
    end
endmodule

Paralelo/banco_paralelo_serial.v
`timescale 1ms/100ps

`include "paralelo_serial.v"
`include "probador_paralelo_serial.v"
`include "synth_paralelo.v"

    module banco_paralelo_serial;
		wire [7:0] in_serial;
		wire clk_4f, clk_32f, valid_in, out_serial_conductual, out_serial, reset;

		paralelo_serial p_s(/*AUTOINST*/
				    // Outputs
				    .out_serial_conductual(out_serial_conductual),
				    // Inputs
				    .clk_4f		(clk_4f),
				    .clk_32f		(clk_32f),
				    .in_serial		(in_serial[7:0]),
				    .valid_in		(valid_in),
				    .reset		(reset));

		
		synth_paralelo estructural(/*AUTOINST*/
					   // Outputs
					   .out_serial_estructural(out_serial_estructural),
					   // Inputs
					   .clk_32f		(clk_32f),
					   .clk_4f		(clk_4f),
					   .in_serial		(in_serial[7:0]),
					   .reset		(reset),
					   .valid_in		(valid_in));

		
		probador_paralelo_serial prob_paralelo_serial(/*AUTOINST*/
							      // Outputs
							      .clk_4f		(clk_4f),
							      .reset		(reset),
							      .valid_in		(valid_in),
							      .in_serial	(in_serial[7:0]),
							      .clk_32f		(clk_32f),
							      // Inputs
							      .out_serial_conductual(out_serial_conductual),
							      .out_serial_estructural(out_serial_estructural));

    endmodule

Paralelo/paraleloserial.vcd
$date
	Sun May 30 22:20:26 2021
$end
$version
	Icarus Verilog
$end
$timescale
	100ps
$end
$scope module banco_paralelo_serial $end
$var wire 1 ! valid_in $end
$var wire 1 " reset $end
$var wire 1 # out_serial_estructural $end
$var wire 1 $ out_serial_conductual $end
$var wire 8 % in_serial [7:0] $end
$var wire 1 & clk_4f $end
$var wire 1 ' clk_32f $end
$scope module estructural $end
$var wire 1 ( _005_ $end
$var wire 1 ) _006_ $end
$var wire 1 * _007_ $end
$var wire 1 + _008_ $end
$var wire 1 , _009_ $end
$var wire 1 - _010_ $end
$var wire 1 . _011_ $end
$var wire 1 / _012_ $end
$var wire 1 0 _013_ $end
$var wire 1 1 _014_ $end
$var wire 1 2 _016_ $end
$var wire 1 3 _021_ $end
$var wire 1 4 _022_ $end
$var wire 1 5 _023_ $end
$var wire 1 6 _026_ $end
$var wire 1 7 _027_ $end
$var wire 1 8 _028_ $end
$var wire 1 9 _029_ $end
$var wire 1 : _030_ $end
$var wire 1 ; _031_ $end
$var wire 1 < _032_ $end
$var wire 1 = _033_ $end
$var wire 1 > _034_ $end
$var wire 1 ? _035_ $end
$var wire 1 @ _036_ $end
$var wire 1 A _037_ $end
$var wire 1 B _038_ $end
$var wire 1 C _039_ $end
$var wire 1 D _041_ $end
$var wire 1 E _042_ $end
$var wire 1 F _043_ $end
$var wire 1 G _044_ $end
$var wire 1 H _045_ $end
$var wire 1 I _046_ $end
$var wire 1 J _047_ $end
$var wire 1 K _048_ $end
$var wire 1 L _050_ $end
$var wire 1 M _052_ $end
$var wire 1 N _053_ $end
$var wire 1 O _054_ $end
$var wire 1 P _055_ $end
$var wire 1 Q _056_ $end
$var wire 1 R _057_ $end
$var wire 1 S _058_ $end
$var wire 1 T _059_ $end
$var wire 1 U _065_ $end
$var wire 1 V _066_ $end
$var wire 1 ! valid_in $end
$var wire 1 " reset $end
$var wire 8 W in_serial [7:0] $end
$var wire 1 & clk_4f $end
$var wire 1 ' clk_32f $end
$var wire 32 X _064_ [31:0] $end
$var wire 32 Y _063_ [31:0] $end
$var wire 3 Z _062_ [2:0] $end
$var wire 3 [ _061_ [2:0] $end
$var wire 1 \ _060_ $end
$var wire 1 ] _051_ $end
$var wire 8 ^ _049_ [7:0] $end
$var wire 1 _ _040_ $end
$var wire 3 ` _025_ [2:0] $end
$var wire 3 a _024_ [2:0] $end
$var wire 2 b _020_ [1:0] $end
$var wire 4 c _019_ [3:0] $end
$var wire 2 d _018_ [1:0] $end
$var wire 4 e _017_ [3:0] $end
$var wire 2 f _015_ [1:0] $end
$var wire 32 g _004_ [31:0] $end
$var wire 32 h _003_ [31:0] $end
$var wire 3 i _002_ [2:0] $end
$var wire 3 j _001_ [2:0] $end
$var wire 1 k _000_ $end
$var reg 1 # out_serial_estructural $end
$var reg 3 l selector [2:0] $end
$var reg 3 m selector_2 [2:0] $end
$upscope $end
$scope module p_s $end
$var wire 1 ! valid_in $end
$var wire 1 " reset $end
$var wire 8 n in_serial [7:0] $end
$var wire 1 & clk_4f $end
$var wire 1 ' clk_32f $end
$var reg 1 $ out_serial_conductual $end
$var reg 3 o selector [2:0] $end
$var reg 3 p selector_2 [2:0] $end
$upscope $end
$scope module prob_paralelo_serial $end
$var wire 1 $ out_serial_conductual $end
$var wire 1 # out_serial_estructural $end
$var reg 1 ' clk_32f $end
$var reg 1 & clk_4f $end
$var reg 8 q in_serial [7:0] $end
$var reg 1 " reset $end
$var reg 1 ! valid_in $end
$upscope $end
$upscope $end
$enddefinitions $end
#0
$dumpvars
b0 q
b0 p
b0 o
b0 n
b0 m
b0 l
0k
b0 j
b0 i
b0z001 h
b0z001 g
b1 f
b0 e
b0 d
b1000 c
b10 b
b111 a
b111 `
1_
b0 ^
0]
1\
b0 [
b1 Z
b0z00 Y
b0z00 X
b0 W
1V
1U
1T
0S
0R
0Q
0P
0O
0N
0M
0L
1K
0J
0I
0H
0G
0F
0E
0D
1C
1B
1A
1@
1?
1>
1=
1<
1;
1:
19
18
17
16
05
04
03
12
01
10
1/
1.
0-
1,
1+
1*
1)
0(
1'
1&
b0 %
0$
0#
0"
0!
$end
#10000000
0'
#20000000
1'
#30000000
0'
#40000000
1'
#50000000
0'
#60000000
1'
#70000000
0'
#80000000
1'
0&
#90000000
0'
#100000000
1'
#110000000
0'
#120000000
1'
#130000000
0'
#140000000
1'
#150000000
0'
#160000000
1]
1L
b10 d
b1000 e
b10000000 ^
1k
b1 j
1"
b11001100 %
b11001100 W
b11001100 n
b11001100 q
1'
1&
#170000000
0'
#180000000
0k
0\
0_
0)
1(
02
13
1J
b10 j
b0 f
0<
0K
0,
b10 Z
14
b110 a
1-
b0z010 g
b0z01 X
1#
b1 l
b1 o
1$
1'
#190000000
0'
#200000000
1k
1)
1\
12
1_
1U
b1 f
b11 j
0(
1I
03
0;
b11 Z
0J
0+
1<
b0z011 g
b0z00 X
1,
b101 a
b10 o
0$
b10 l
0#
1'
#210000000
0'
#220000000
1k
1\
1U
1_
1)
12
1H
b100 j
b10 f
0:
0I
0*
b100 Z
1;
b100 a
1+
b0z100 g
b0z11 X
1#
b11 l
b11 o
1$
1'
#230000000
0'
#240000000
1k
1\
1_
1)
12
0(
b101 j
03
0D
0E
0F
1G
1*
b10 f
16
b101 Z
17
18
09
0H
1+
1,
0-
b0z00 X
1:
b11 a
b0z101 g
b100 o
b100 l
1'
0&
#250000000
0'
#260000000
02
1F
b110 j
b0 f
08
0G
0,
b110 Z
19
b10 a
1-
b0z110 g
b0z01 X
b101 l
b101 o
1'
#270000000
0'
#280000000
0k
1(
0\
13
b111 j
1U
0_
1E
0)
07
b111 Z
0F
0+
18
b0z111 g
b0z00 X
1,
b1 a
b110 o
b110 l
1'
#290000000
0'
#300000000
1D
b0 j
03
06
0E
0*
b0 Z
17
b0 a
1+
b0z000 g
b0z11 X
0#
b111 l
b111 o
0$
1'
#310000000
0'
#320000000
0(
1_
1)
12
03
0D
0I
0J
1K
1*
b1 f
16
1;
1<
04
0H
b1 i
1+
1,
0-
b0z00 X
1:
b111 a
b0z001 g
1k
b1 [
1\
b0 o
b0 l
b10101011 %
b10101011 W
b10101011 n
b10101011 q
1!
1'
1&
#330000000
0'
#340000000
0k
0L
0\
0]
b0 d
1V
b0 e
b10 b
1S
b10 i
b0 ^
b1000 c
0C
0T
00
b10 [
15
b110 `
11
b0z010 h
b0z01 Y
1#
b1 m
b1 p
1$
1'
#350000000
0'
#360000000
1L
1k
1\
b10 d
1]
1V
b100 e
b10 b
b100000 ^
b11 i
1R
b100 c
0B
b11 [
0S
0/
1C
b0z011 h
b0z00 Y
10
b101 `
b10 p
0$
b10 m
0#
1'
#370000000
0'
#380000000
0k
0L
0\
0]
b0 d
1V
b0 e
b10 b
1Q
b100 i
b0 ^
b100 c
0A
0R
0.
b100 [
1B
b100 `
1/
b0z100 h
b0z11 Y
1#
b11 m
b11 p
1$
1'
#390000000
0'
#400000000
1L
1k
1\
b1 d
1]
1V
b10 e
b1 b
b101 i
b1000 ^
0M
0N
0O
1P
1.
b10 c
1=
b101 [
1>
1?
0@
0Q
1/
10
01
b0z00 Y
1A
b11 `
b0z101 h
b100 p
0$
b100 m
0#
1'
0&
#410000000
0'
#420000000
0k
0L
0\
0]
b0 d
1V
b0 e
b1 b
1O
b110 i
b0 ^
b10 c
0?
0P
00
b110 [
1@
b10 `
11
b0z110 h
b0z01 Y
1#
b101 m
b101 p
1$
1'
#430000000
0'
#440000000
1L
1k
1\
b1 d
1]
1V
b1 e
b1 b
b10 ^
b111 i
1N
b1 c
0>
b111 [
0O
0/
1?
b0z111 h
b0z00 Y
10
b1 `
b110 p
0$
b110 m
0#
1'
#450000000
0'
#460000000
1k
1L
1\
1]
b1 d
1V
b1 e
b1 b
1M
b0 i
b1 ^
b1 c
0=
0N
0.
b0 [
1>
b0 `
1/
b0z000 h
b0z11 Y
1#
b111 m
b111 p
1$
1'
#470000000
0'
#480000000
1k
1\
1]
1L
b10 b
b1 i
b10 d
0M
0R
0S
1T
1.
b1000 c
1=
b1 [
b1000 e
1B
1C
05
0Q
1/
10
01
b0z00 Y
1A
b111 `
b0z001 h
b10000000 ^
b0 p
b0 m
b11001010 %
b11001010 W
b11001010 n
b11001010 q
1'
1&
#490000000
0'
#500000000
1k
1L
1\
1]
b10 d
1V
b1000 e
b10 b
1S
b10 i
b1000000 ^
b1000 c
0C
0T
00
b10 [
15
b110 `
11
b0z010 h
b0z01 Y
b1 m
b1 p
1'
#510000000
0'
#520000000
0k
0L
0\
0]
b0 d
1V
b0 e
b10 b
b11 i
1R
b0 ^
b100 c
0B
b11 [
0S
0/
1C
b0z011 h
b0z00 Y
10
b101 `
b10 p
b10 m
1'
#530000000
0'
#540000000
0k
0\
0]
1V
b10 b
1Q
b100 i
b100 c
0A
0R
0.
b100 [
1B
b100 `
1/
b0z100 h
b0z11 Y
0#
b11 m
b11 p
0$
1'
#550000000
0'
#560000000
1L
1k
1\
b1 d
1]
1V
b10 e
b1 b
b101 i
b1000 ^
0M
0N
0O
1P
1.
b10 c
1=
b101 [
1>
1?
0@
0Q
1/
10
01
b0z00 Y
1A
b11 `
b0z101 h
b100 p
b100 m
1'
0&
#570000000
0'
#580000000
0k
0L
0\
0]
b0 d
1V
b0 e
b1 b
1O
b110 i
b0 ^
b10 c
0?
0P
00
b110 [
1@
b10 `
11
b0z110 h
b0z01 Y
1#
b101 m
b101 p
1$
1'
#590000000
0'
#600000000
1L
1k
1\
b1 d
1]
1V
b1 e
b1 b
b10 ^
b111 i
1N
b1 c
0>
b111 [
0O
0/
1?
b0z111 h
b0z00 Y
10
b1 `
b110 p
0$
b110 m
0#
1'
#610000000
0'
#620000000
0k
0L
0\
0]
b0 d
1V
b0 e
b1 b
1M
b0 i
b0 ^
b1 c
0=
0N
0.
b0 [
1>
b0 `
1/
b0z000 h
b0z11 Y
1#
b111 m
b111 p
1$
1'
#630000000
0'
#640000000
0k
0\
0]
0L
b0 d
b0 e
b10 b
b1 i
0M
0R
0S
1T
1.
b0 ^
b1000 c
1=
b1 [
1B
1C
05
0Q
1/
10
01
b0z00 Y
1A
b111 `
b0z001 h
b0 p
0$
b0 m
0#
b10010 %
b10010 W
b10010 n
b10010 q
1'
1&
#650000000
0'
#660000000
0k
0\
0]
1V
b10 b
1S
b10 i
b1000 c
0C
0T
00
b10 [
15
b110 `
11
b0z010 h
b0z01 Y
b1 m
b1 p
1'
#670000000
0'
#680000000
0k
0\
0]
1V
b10 b
b11 i
1R
b100 c
0B
b11 [
0S
0/
1C
b0z011 h
b0z00 Y
10
b101 `
b10 p
b10 m
1'
#690000000
0'
#700000000
1L
1k
1\
b10 d
1]
1V
b100 e
b10 b
b10000 ^
1Q
b100 i
b100 c
0A
0R
0.
b100 [
1B
b100 `
1/
b0z100 h
b0z11 Y
b11 m
b11 p
1'
#710000000
0'
#720000000
0k
0L
0\
0]
b0 d
1V
b0 e
b1 b
b101 i
0M
0N
0O
1P
1.
b0 ^
b10 c
1=
b101 [
1>
1?
0@
0Q
1/
10
01
b0z00 Y
1A
b11 `
b0z101 h
b100 p
1$
b100 m
1#
1'
0&
#730000000
0'
#740000000
0k
0\
0]
1V
b1 b
1O
b110 i
b10 c
0?
0P
00
b110 [
1@
b10 `
11
b0z110 h
b0z01 Y
0#
b101 m
b101 p
0$
1'
#750000000
0'
#760000000
1L
1k
1\
b1 d
1]
1V
b1 e
b1 b
b10 ^
b111 i
1N
b1 c
0>
b111 [
0O
0/
1?
b0z111 h
b0z00 Y
10
b1 `
b110 p
b110 m
1'
#770000000
0'
#780000000
0k
0L
0\
0]
b0 d
1V
b0 e
b1 b
1M
b0 i
b0 ^
b1 c
0=
0N
0.
b0 [
1>
b0 `
1/
b0z000 h
b0z11 Y
1#
b111 m
b111 p
1$
1'
#790000000
0'
