Muxes/cmos_cells.v
`timescale 	1ns	/ 100ps
module BUF(A, Y);
input A;
output Y;
assign Y = A;
endmodule

module NOT(A, Y);
input A;
output Y;
assign #3.3 Y = ~A;
endmodule

module NAND(A, B, Y);
input A, B;
output Y;
assign #9 Y = ~(A & B);
endmodule

module NOR(A, B, Y);
input A, B;
output Y;
assign #6 Y = ~(A | B);
endmodule

module DFF(C, D, Q);
input C, D;
output reg Q;
always @(posedge C)
	#6 Q <= D;
endmodule

module DFFSR(C, D, Q, S, R);
input C, D, S, R;
output reg Q;
always @(posedge C, posedge S, posedge R)
	if (S)
		Q <= 1'b1;
	else if (R)
		Q <= 1'b0;
	else
		Q <= D;
endmodule

Muxes/Probador_mux.v
module Probador_mux(input [7:0] Salida_estructural,
                    input [7:0] Salida_conductual,
						input validSalida0,
						input validSalida1,
						output reg  validEntrada0,
                        output reg  validEntrada1,
                        output reg  validEntrada2,
                        output reg validEntrada3,
                        output reg  [7:0] Entrada0,
						output reg [7:0] Entrada1,
                        output reg [7:0] Entrada2,
						output reg [7:0] Entrada3,
						output reg clk_4f,
						output reg clk_2f,
						output reg clk_f,
						output reg reset);
	initial begin
	$dumpfile("muxL2.vcd");
	$dumpvars;

	{validEntrada0,validEntrada1,validEntrada2,validEntrada3, reset} <= 0;
	{Entrada0} <= 8'h00;
    {Entrada1} <= 8'h00;
    {Entrada2} <= 8'h00;
    {Entrada3} <= 8'h00;
 
	
	@(posedge clk_2f);

 
	//valid <= 1;
	//data_in <= 32'hEEFF9900;

	@(posedge clk_f);
	reset <= 1;
    validEntrada0 <= 1;
	validEntrada1 <= 1;
    validEntrada2 <= 1;
    validEntrada3 <= 1;


	/*Entrada <= 8'hEE;*/
    {Entrada0} <= 8'hEE;
    {Entrada1} <={Entrada1}+1;
    {Entrada2} <=8'hFF;
    {Entrada3} <=8'hFD;



	@(posedge clk_f);
	validEntrada0 <= 1;
    validEntrada1 <= 1;
    validEntrada2 <= 1;
    validEntrada3 <= 1;
    
	 
    
    {Entrada0} <={Entrada0}+1;
    {Entrada1} <={Entrada1}+1;
    {Entrada2} <={Entrada2}+1;
    {Entrada3} <={Entrada3}+1;
      

 

	@(posedge clk_f);
	validEntrada0 <= 1;
    validEntrada1 <= 1;
    validEntrada2 <= 1;
    validEntrada3 <= 1;


    {Entrada0} <={Entrada0}+1;
    {Entrada1} <={Entrada1}+1;
    {Entrada2} <={Entrada2}+1;
    {Entrada3} <={Entrada3}+1;




    
	@(posedge clk_f);
	validEntrada0 <= 1;
    validEntrada1 <= 1;
    validEntrada2 <= 1;
    validEntrada3 <= 1;


	{Entrada0} <={Entrada0}+1;
    {Entrada1} <={Entrada1}+1;
    {Entrada2} <={Entrada2}+1;
    {Entrada3} <={Entrada3}+1;


	@(posedge clk_f);
	validEntrada0 <= 1;
    validEntrada1 <= 1;
    validEntrada2 <= 1;
    validEntrada3 <= 1;


	{Entrada0} <={Entrada0}+1;
    {Entrada1} <={Entrada1}+1;
    {Entrada2} <={Entrada2}+1;
    {Entrada3} <={Entrada3}+1;
     

	@(posedge clk_f);
	validEntrada0 <= 1;
    validEntrada1 <= 1;
    validEntrada2 <= 1;
    validEntrada3 <= 1;



	{Entrada0} <={Entrada0}+1;
    {Entrada1} <={Entrada1}+1;
    {Entrada2} <={Entrada2}+1;
    {Entrada3} <={Entrada3}+1;


	@(posedge clk_f);
	$finish;
	end
	
	initial clk_4f <= 0;
	always #1 clk_4f <= ~clk_4f;

	initial clk_2f <= 0;
	always #2 clk_2f <= ~clk_2f;

	initial clk_f <= 0;
	always #4 clk_f <= ~clk_f;


endmodule

Muxes/synth.v
/* Generated by Yosys 0.9 (git sha1 1979e0b) */

(* top =  1  *)
(* src = "synth.v:4" *)
module synth(Salida_estructural, validsalida0, validsalida1, validEntrada0, validEntrada1, validEntrada2, validEntrada3, Entrada0, Entrada1, Entrada2, Entrada3, clk_4f, clk_2f, clk_f, reset);
  (* src = "synth.v:12" *)
  input [7:0] Entrada0;
  (* src = "synth.v:13" *)
  input [7:0] Entrada1;
  (* src = "synth.v:14" *)
  input [7:0] Entrada2;
  (* src = "synth.v:15" *)
  input [7:0] Entrada3;
  (* src = "synth.v:22" *)
  wire [7:0] Salida0;
  (* src = "synth.v:22" *)
  wire [7:0] Salida1;
  (* src = "synth.v:5" *)
  output [7:0] Salida_estructural;
  (* src = "synth.v:17" *)
  input clk_2f;
  (* src = "synth.v:16" *)
  input clk_4f;
  (* src = "synth.v:18" *)
  input clk_f;
  (* src = "synth.v:19" *)
  input reset;
  (* src = "synth.v:8" *)
  input validEntrada0;
  (* src = "synth.v:9" *)
  input validEntrada1;
  (* src = "synth.v:10" *)
  input validEntrada2;
  (* src = "synth.v:11" *)
  input validEntrada3;
  (* src = "synth.v:6" *)
  output validsalida0;
  (* src = "synth.v:7" *)
  output validsalida1;
  (* module_not_derived = 32'd1 *)
  (* src = "synth.v:39" *)
  synth3 muxitol2 (
    .Entrada0(Salida0),
    .Entrada1(Salida1),
    .Salida_estructural(Salida_estructural),
    .clk_4f(clk_4f),
    .reset(reset),
    .validEntrada0(validEntrada0),
    .validEntrada1(validEntrada1),
    .validsalida(validsalida0)
  );
  (* module_not_derived = 32'd1 *)
  (* src = "synth.v:23" *)
  synth2 muxl1 (
    .Entrada0(Entrada0),
    .Entrada1(Entrada1),
    .Entrada2(Entrada2),
    .Entrada3(Entrada3),
    .Salida0(Salida0),
    .Salida1(Salida1),
    .clk_2f(clk_2f),
    .reset(reset),
    .validEntrada0(validEntrada0),
    .validEntrada1(validEntrada1),
    .validEntrada2(validEntrada2),
    .validEntrada3(validEntrada3),
    .validsalida0(validsalida0),
    .validsalida1(validsalida1)
  );
endmodule

(* src = "synth1.v:1" *)
module synth1(Salida_estructural, validsalida, Entrada0, Entrada1, validEntrada0, validEntrada1, clk, reset);
  (* src = "synth1.v:12" *)
  wire [7:0] _00_;
  (* src = "synth1.v:12" *)
  wire _01_;
  wire [7:0] _02_;
  wire [7:0] _03_;
  wire _04_;
  wire [7:0] _05_;
  (* src = "synth1.v:4" *)
  input [7:0] Entrada0;
  (* src = "synth1.v:5" *)
  input [7:0] Entrada1;
  (* src = "synth1.v:1" *)
  output [7:0] Salida_estructural;
  reg [7:0] Salida_estructural;
  (* src = "synth1.v:8" *)
  input clk;
  (* src = "synth1.v:9" *)
  input reset;
  (* src = "synth1.v:11" *)
  reg selector;
  (* src = "synth1.v:6" *)
  input validEntrada0;
  (* src = "synth1.v:7" *)
  input validEntrada1;
  (* src = "synth1.v:2" *)
  output validsalida;
  always @(posedge clk)
      selector <= _01_;
  always @(posedge clk)
      Salida_estructural <= _00_;
  assign _02_ = validEntrada0 ? (* full_case = 32'd1 *) (* src = "synth1.v:17" *) Entrada0 : 8'h00;
  assign _03_ = selector ? (* full_case = 32'd1 *) (* src = "synth1.v:16" *) _05_ : _02_;
  assign _00_ = reset ? (* full_case = 32'd1 *) (* src = "synth1.v:15" *) _03_ : 8'h00;
  assign _04_ = selector ? (* full_case = 32'd1 *) (* src = "synth1.v:16" *) 1'h0 : 1'h1;
  assign _01_ = reset ? (* full_case = 32'd1 *) (* src = "synth1.v:15" *) _04_ : selector;
  assign _05_ = validEntrada1 ? (* full_case = 32'd1 *) (* src = "synth1.v:25" *) Entrada1 : 8'h00;
endmodule

(* src = "synth2.v:4" *)
module synth2(Salida0, Salida1, validsalida0, validsalida1, Entrada0, Entrada1, Entrada2, Entrada3, validEntrada0, validEntrada1, validEntrada2, validEntrada3, clk_2f, reset);
  (* src = "synth2.v:9" *)
  input [7:0] Entrada0;
  (* src = "synth2.v:10" *)
  input [7:0] Entrada1;
  (* src = "synth2.v:11" *)
  input [7:0] Entrada2;
  (* src = "synth2.v:12" *)
  input [7:0] Entrada3;
  (* src = "synth2.v:5" *)
  output [7:0] Salida0;
  (* src = "synth2.v:6" *)
  output [7:0] Salida1;
  (* src = "synth2.v:17" *)
  input clk_2f;
  (* src = "synth2.v:18" *)
  input reset;
  (* src = "synth2.v:13" *)
  input validEntrada0;
  (* src = "synth2.v:14" *)
  input validEntrada1;
  (* src = "synth2.v:15" *)
  input validEntrada2;
  (* src = "synth2.v:16" *)
  input validEntrada3;
  (* src = "synth2.v:7" *)
  output validsalida0;
  (* src = "synth2.v:8" *)
  output validsalida1;
  (* module_not_derived = 32'd1 *)
  (* src = "synth2.v:20" *)
  synth1 mux1 (
    .Entrada0(Entrada0),
    .Entrada1(Entrada1),
    .Salida_estructural(Salida0),
    .clk(clk_2f),
    .reset(reset),
    .validEntrada0(validEntrada0),
    .validEntrada1(validEntrada1),
    .validsalida(validsalida0)
  );
  (* module_not_derived = 32'd1 *)
  (* src = "synth2.v:32" *)
  synth1 mux2 (
    .Entrada0(Entrada2),
    .Entrada1(Entrada3),
    .Salida_estructural(Salida1),
    .clk(clk_2f),
    .reset(reset),
    .validEntrada0(validEntrada2),
    .validEntrada1(validEntrada3),
    .validsalida(validsalida1)
  );
endmodule

(* src = "synth3.v:5" *)
module synth3(Salida_estructural, validsalida, Entrada0, Entrada1, validEntrada0, validEntrada1, clk_4f, reset);
  (* src = "synth3.v:8" *)
  input [7:0] Entrada0;
  (* src = "synth3.v:9" *)
  input [7:0] Entrada1;
  (* src = "synth3.v:6" *)
  output [7:0] Salida_estructural;
  (* src = "synth3.v:12" *)
  input clk_4f;
  (* src = "synth3.v:13" *)
  input reset;
  (* src = "synth3.v:10" *)
  input validEntrada0;
  (* src = "synth3.v:11" *)
  input validEntrada1;
  (* src = "synth3.v:7" *)
  output validsalida;
  (* module_not_derived = 32'd1 *)
  (* src = "synth3.v:15" *)
  synth1 mux1 (
    .Entrada0(Entrada0),
    .Entrada1(Entrada1),
    .Salida_estructural(Salida_estructural),
    .clk(clk_4f),
    .reset(reset),
    .validEntrada0(validEntrada0),
    .validEntrada1(validEntrada1),
    .validsalida(validsalida)
  );
endmodule

Muxes/mux2x1.v
module mux2x1 (output reg [7:0] Salida_conductual,
            output reg validsalida,
            
	    input [7:0] Entrada0,
            input [7:0] Entrada1,
            input validEntrada0,
            input validEntrada1,
            input clk,
            input reset);
            
reg selector;        
        always@(posedge clk) begin
           
        
                if (reset==1)begin //Si el reset es 1 el flop puede tomar el valor de alguna de las dos entradas
                    if(selector==0)begin
                        if (validEntrada0==1)
                            Salida_conductual<=Entrada0; // Segun el valor del selector este dato irá a la salida del flop
                        else 
                            Salida_conductual<=0;
                    selector<=1;  //Cambia para toamr Entrada1
                    end    

                    else begin
                        if(validEntrada1==1)
                        Salida_conductual<=Entrada1;
                        else begin
                            
                            Salida_conductual<=0;
                        end
                    selector<=0;//Cambia para tomar entrada 0
                    end
                end    
                else
                Salida_conductual<=0; //Condicion dada en el enunciado, si el reset es cero el flop toma valor de 00
            end
endmodule

Muxes/muxL2.v
//se incluye el mux mas pequeño

    
//Se crea el mux de 4 entradas (bus de 8 bits cada una) y 2 salidas(bus de 8 bits),con sus respectivos valid tanto en entradas como salidas
module muxL2(
    output [7:0]Salida_conductual,
    output validsalida,
    input [7:0]Entrada0,
    input [7:0]Entrada1,
    input validEntrada0,
    input validEntrada1,
    input clk_4f,
    input reset);

    mux2x1 mux1(
        //Salidas
        .Salida_conductual  (Salida_conductual[7:0]),  
        .validsalida (validsalida),
        //Entradas
        .Entrada0    (Entrada0[7:0]),
        .Entrada1   (Entrada1[7:0]),
        .validEntrada0   (validEntrada0),
        .validEntrada1    (validEntrada1),
        .clk       (clk_4f),
        .reset     (reset)
    );
endmodule

Muxes/muxL1.v
//se incluye el mux mas pequeño
//`include "mux2x1.v"
//Se crea el mux de 4 entradas (bus de 8 bits cada una) y 2 salidas(bus de 8 bits),con sus respectivos valid tanto en entradas como salidas
module muxL1(
    output  [7:0]Salida0,
    output [7:0]Salida1,
    output validsalida0,
    output validsalida1,
    input [7:0]Entrada0,
    input [7:0]Entrada1,
    input [7:0]Entrada2,
    input [7:0]Entrada3,
    input validEntrada0,
    input validEntrada1,
    input validEntrada2,
    input validEntrada3,
    input clk_2f,
    input reset);

    mux2x1 mux1(
        //Salidas
        .Salida_conductual  (Salida0[7:0]),  
        .validsalida (validsalida0),
        //Entradas
        .Entrada0    (Entrada0[7:0]),
        .Entrada1   (Entrada1[7:0]),
        .validEntrada0   (validEntrada0),
        .validEntrada1    (validEntrada1),
        .clk       (clk_2f),
        .reset     (reset)
    );
    mux2x1 mux2(
        //Salidas
        .Salida_conductual  (Salida1[7:0]),  
        .validsalida (validsalida1),
        //Entradas
        .Entrada0    (Entrada2[7:0]),
        .Entrada1   (Entrada3[7:0]),
        .validEntrada0   (validEntrada2),
        .validEntrada1    (validEntrada3),

        .clk       (clk_2f),
        .reset     (reset)
    );
endmodule

Muxes/Muxes.v
`include "mux2x1.v"
`include "muxL2.v"
`include "muxL1.v"
module Muxes(
                        output  [7:0]Salida_conductual,
					    output validsalida0,
						output validsalida1,
						input validEntrada0,
                        input validEntrada1,
                        input validEntrada2,
                        input validEntrada3,
                        input [7:0]Entrada0,
						input [7:0]Entrada1,
                        input [7:0]Entrada2,
						input [7:0]Entrada3,
						input clk_4f,
						input clk_2f,
						input clk_f,
						input reset
                     
    );
    wire [7:0] Salida0, Salida1;
    muxL1 muxl1( .clk_2f(clk_2f),
    .reset (reset),
    .validsalida0(validsalida0),
    .validsalida1(validsalida1),
    .validEntrada0(validEntrada0),
    .validEntrada1(validEntrada1),
     .validEntrada2(validEntrada2),
    .validEntrada3(validEntrada3),
    .Entrada0(Entrada0[7:0]), 
    .Entrada1(Entrada1[7:0]), 
    .Entrada2(Entrada2[7:0]), 
    .Entrada3(Entrada3[7:0]), 
    .Salida0(Salida0[7:0]),
    .Salida1(Salida1[7:0]));


    muxL2 muxitol2( .Salida_conductual(Salida_conductual[7:0]),
    .validsalida(validsalida0),
    .Entrada0(Salida0[7:0]),
    .Entrada1(Salida1[7:0]),
    .validEntrada0(validEntrada0),
    .validEntrada1(validEntrada1),
    .clk_4f(clk_4f),
    .reset (reset)



    );
endmodule

Muxes/BancoPruebas_Mux.v
`timescale 1ms/100ps

//`include "demux8_32_v2.v"
`include "Probador_mux.v"
`include "Muxes.v"

/*`include "muxL2.v"*/
`include "synth.v"

/*`include "../lib/cmos_cells.v"*/

module banco_mux;

	wire [7:0] Salida_conductual,Salida_estructural,Salida0,Salida1;
	wire [7:0] Entrada0, Entrada1,Entrada2,Entrada3;
	wire clk_f,clk_2f, clk_4f, validSalida0, validSalida1, validEntrada1,validEntrada0,validEntrada2,validEntrada3;


      

        Muxes muxes1(/*AUTOINST*/
		     // Outputs
		     .Salida_conductual	(Salida_conductual[7:0]),
		     .validsalida0	(validsalida0),
		     .validsalida1	(validsalida1),
		     // Inputs
		     .validEntrada0	(validEntrada0),
		     .validEntrada1	(validEntrada1),
		     .validEntrada2	(validEntrada2),
		     .validEntrada3	(validEntrada3),
		     .Entrada0		(Entrada0[7:0]),
		     .Entrada1		(Entrada1[7:0]),
		     .Entrada2		(Entrada2[7:0]),
		     .Entrada3		(Entrada3[7:0]),
		     .clk_4f		(clk_4f),
		     .clk_2f		(clk_2f),
		     .clk_f		(clk_f),
		     .reset		(reset));



        synth muxes2(
          /*AUTOINST*/
		     // Outputs
		     .Salida_estructural(Salida_estructural[7:0]),
		     .validsalida0	(validsalida0),
		     .validsalida1	(validsalida1),
		     // Inputs
		     .Entrada0		(Entrada0[7:0]),
		     .Entrada1		(Entrada1[7:0]),
		     .Entrada2		(Entrada2[7:0]),
		     .Entrada3		(Entrada3[7:0]),
		     .clk_2f		(clk_2f),
		     .clk_4f		(clk_4f),
		     .clk_f		(clk_f),
		     .reset		(reset),
		     .validEntrada0	(validEntrada0),
		     .validEntrada1	(validEntrada1),
		     .validEntrada2	(validEntrada2),
		     .validEntrada3	(validEntrada3));

    Probador_mux probador(/*AUTOINST*/
			  // Outputs
			  .validEntrada0	(validEntrada0),
			  .validEntrada1	(validEntrada1),
			  .validEntrada2	(validEntrada2),
			  .validEntrada3	(validEntrada3),
			  .Entrada0		(Entrada0[7:0]),
			  .Entrada1		(Entrada1[7:0]),
			  .Entrada2		(Entrada2[7:0]),
			  .Entrada3		(Entrada3[7:0]),
			  .clk_4f		(clk_4f),
			  .clk_2f		(clk_2f),
			  .clk_f		(clk_f),
			  .reset		(reset),
			  // Inputs
			  .Salida_estructural	(Salida_estructural[7:0]),
			  .Salida_conductual	(Salida_conductual[7:0]),
			  .validSalida0		(validSalida0),
			  .validSalida1		(validSalida1));

endmodule

Muxes/muxL2.vcd
$date
	Sat Jun  5 09:48:39 2021
$end
$version
	Icarus Verilog
$end
$timescale
	100ps
$end
$scope module banco_mux $end
$var wire 1 ! validSalida0 $end
$var wire 1 " validSalida1 $end
$var wire 1 # validsalida0 $end
$var wire 1 $ validsalida1 $end
$var wire 1 % validEntrada3 $end
$var wire 1 & validEntrada2 $end
$var wire 1 ' validEntrada1 $end
$var wire 1 ( validEntrada0 $end
$var wire 1 ) reset $end
$var wire 1 * clk_f $end
$var wire 1 + clk_4f $end
$var wire 1 , clk_2f $end
$var wire 8 - Salida_estructural [7:0] $end
$var wire 8 . Salida_conductual [7:0] $end
$var wire 8 / Entrada3 [7:0] $end
$var wire 8 0 Entrada2 [7:0] $end
$var wire 8 1 Entrada1 [7:0] $end
$var wire 8 2 Entrada0 [7:0] $end
$scope module muxes1 $end
$var wire 1 # validsalida0 $end
$var wire 1 $ validsalida1 $end
$var wire 1 % validEntrada3 $end
$var wire 1 & validEntrada2 $end
$var wire 1 ' validEntrada1 $end
$var wire 1 ( validEntrada0 $end
$var wire 1 ) reset $end
$var wire 1 * clk_f $end
$var wire 1 + clk_4f $end
$var wire 1 , clk_2f $end
$var wire 8 3 Salida_conductual [7:0] $end
$var wire 8 4 Salida1 [7:0] $end
$var wire 8 5 Salida0 [7:0] $end
$var wire 8 6 Entrada3 [7:0] $end
$var wire 8 7 Entrada2 [7:0] $end
$var wire 8 8 Entrada1 [7:0] $end
$var wire 8 9 Entrada0 [7:0] $end
$scope module muxitol2 $end
$var wire 1 # validsalida $end
$var wire 1 ' validEntrada1 $end
$var wire 1 ( validEntrada0 $end
$var wire 1 ) reset $end
$var wire 1 + clk_4f $end
$var wire 8 : Salida_conductual [7:0] $end
$var wire 8 ; Entrada1 [7:0] $end
$var wire 8 < Entrada0 [7:0] $end
$scope module mux1 $end
$var wire 1 ' validEntrada1 $end
$var wire 1 ( validEntrada0 $end
$var wire 1 ) reset $end
$var wire 1 + clk $end
$var wire 8 = Entrada1 [7:0] $end
$var wire 8 > Entrada0 [7:0] $end
$var reg 8 ? Salida_conductual [7:0] $end
$var reg 1 @ selector $end
$var reg 1 A validsalida $end
$upscope $end
$upscope $end
$scope module muxl1 $end
$var wire 1 # validsalida0 $end
$var wire 1 $ validsalida1 $end
$var wire 1 % validEntrada3 $end
$var wire 1 & validEntrada2 $end
$var wire 1 ' validEntrada1 $end
$var wire 1 ( validEntrada0 $end
$var wire 1 ) reset $end
$var wire 1 , clk_2f $end
$var wire 8 B Salida1 [7:0] $end
$var wire 8 C Salida0 [7:0] $end
$var wire 8 D Entrada3 [7:0] $end
$var wire 8 E Entrada2 [7:0] $end
$var wire 8 F Entrada1 [7:0] $end
$var wire 8 G Entrada0 [7:0] $end
$scope module mux1 $end
$var wire 1 ' validEntrada1 $end
$var wire 1 ( validEntrada0 $end
$var wire 1 ) reset $end
$var wire 1 , clk $end
$var wire 8 H Entrada1 [7:0] $end
$var wire 8 I Entrada0 [7:0] $end
$var reg 8 J Salida_conductual [7:0] $end
$var reg 1 K selector $end
$var reg 1 L validsalida $end
$upscope $end
$scope module mux2 $end
$var wire 1 % validEntrada1 $end
$var wire 1 & validEntrada0 $end
$var wire 1 ) reset $end
$var wire 1 , clk $end
$var wire 8 M Entrada1 [7:0] $end
$var wire 8 N Entrada0 [7:0] $end
$var reg 8 O Salida_conductual [7:0] $end
$var reg 1 P selector $end
$var reg 1 $ validsalida $end
$upscope $end
$upscope $end
$upscope $end
$scope module muxes2 $end
$var wire 1 # validsalida0 $end
$var wire 1 $ validsalida1 $end
$var wire 1 % validEntrada3 $end
$var wire 1 & validEntrada2 $end
$var wire 1 ' validEntrada1 $end
$var wire 1 ( validEntrada0 $end
$var wire 1 ) reset $end
$var wire 1 * clk_f $end
$var wire 1 + clk_4f $end
$var wire 1 , clk_2f $end
$var wire 8 Q Salida_estructural [7:0] $end
$var wire 8 R Salida1 [7:0] $end
$var wire 8 S Salida0 [7:0] $end
$var wire 8 T Entrada3 [7:0] $end
$var wire 8 U Entrada2 [7:0] $end
$var wire 8 V Entrada1 [7:0] $end
$var wire 8 W Entrada0 [7:0] $end
$scope module muxitol2 $end
$var wire 1 # validsalida $end
$var wire 1 ' validEntrada1 $end
$var wire 1 ( validEntrada0 $end
$var wire 1 ) reset $end
$var wire 1 + clk_4f $end
$var wire 8 X Salida_estructural [7:0] $end
$var wire 8 Y Entrada1 [7:0] $end
$var wire 8 Z Entrada0 [7:0] $end
$scope module mux1 $end
$var wire 1 # validsalida $end
$var wire 1 ' validEntrada1 $end
$var wire 1 ( validEntrada0 $end
$var wire 1 ) reset $end
$var wire 1 + clk $end
$var wire 8 [ _05_ [7:0] $end
$var wire 1 \ _04_ $end
$var wire 8 ] _03_ [7:0] $end
$var wire 8 ^ _02_ [7:0] $end
$var wire 1 _ _01_ $end
$var wire 8 ` _00_ [7:0] $end
$var wire 8 a Entrada1 [7:0] $end
$var wire 8 b Entrada0 [7:0] $end
$var reg 8 c Salida_estructural [7:0] $end
$var reg 1 d selector $end
$upscope $end
$upscope $end
$scope module muxl1 $end
$var wire 1 # validsalida0 $end
$var wire 1 $ validsalida1 $end
$var wire 1 % validEntrada3 $end
$var wire 1 & validEntrada2 $end
$var wire 1 ' validEntrada1 $end
$var wire 1 ( validEntrada0 $end
$var wire 1 ) reset $end
$var wire 1 , clk_2f $end
$var wire 8 e Salida1 [7:0] $end
$var wire 8 f Salida0 [7:0] $end
$var wire 8 g Entrada3 [7:0] $end
$var wire 8 h Entrada2 [7:0] $end
$var wire 8 i Entrada1 [7:0] $end
$var wire 8 j Entrada0 [7:0] $end
$scope module mux1 $end
$var wire 1 # validsalida $end
$var wire 1 ' validEntrada1 $end
$var wire 1 ( validEntrada0 $end
$var wire 1 ) reset $end
$var wire 1 , clk $end
$var wire 8 k _05_ [7:0] $end
$var wire 1 l _04_ $end
$var wire 8 m _03_ [7:0] $end
$var wire 8 n _02_ [7:0] $end
$var wire 1 o _01_ $end
$var wire 8 p _00_ [7:0] $end
$var wire 8 q Entrada1 [7:0] $end
$var wire 8 r Entrada0 [7:0] $end
$var reg 8 s Salida_estructural [7:0] $end
$var reg 1 t selector $end
$upscope $end
$scope module mux2 $end
$var wire 1 $ validsalida $end
$var wire 1 % validEntrada1 $end
$var wire 1 & validEntrada0 $end
$var wire 1 ) reset $end
$var wire 1 , clk $end
$var wire 8 u _05_ [7:0] $end
$var wire 1 v _04_ $end
$var wire 8 w _03_ [7:0] $end
$var wire 8 x _02_ [7:0] $end
$var wire 1 y _01_ $end
$var wire 8 z _00_ [7:0] $end
$var wire 8 { Entrada1 [7:0] $end
$var wire 8 | Entrada0 [7:0] $end
$var reg 8 } Salida_estructural [7:0] $end
$var reg 1 ~ selector $end
$upscope $end
$upscope $end
$upscope $end
$scope module probador $end
$var wire 8 !" Salida_conductual [7:0] $end
$var wire 8 "" Salida_estructural [7:0] $end
$var wire 1 ! validSalida0 $end
$var wire 1 " validSalida1 $end
$var reg 8 #" Entrada0 [7:0] $end
$var reg 8 $" Entrada1 [7:0] $end
$var reg 8 %" Entrada2 [7:0] $end
$var reg 8 &" Entrada3 [7:0] $end
$var reg 1 , clk_2f $end
$var reg 1 + clk_4f $end
$var reg 1 * clk_f $end
$var reg 1 ) reset $end
$var reg 1 ( validEntrada0 $end
$var reg 1 ' validEntrada1 $end
$var reg 1 & validEntrada2 $end
$var reg 1 % validEntrada3 $end
$upscope $end
$upscope $end
$enddefinitions $end
#0
$dumpvars
b0 &"
b0 %"
b0 $"
b0 #"
bx ""
bx !"
x~
bx }
b0 |
b0 {
b0 z
xy
b0 x
b0 w
xv
b0 u
xt
bx s
b0 r
b0 q
b0 p
xo
b0 n
b0 m
xl
b0 k
b0 j
b0 i
b0 h
b0 g
bx f
bx e
xd
bx c
bx b
bx a
b0 `
x_
b0 ^
b0 ]
x\
b0 [
bx Z
bx Y
bx X
b0 W
b0 V
b0 U
b0 T
bx S
bx R
bx Q
xP
bx O
b0 N
b0 M
xL
xK
bx J
b0 I
b0 H
b0 G
b0 F
b0 E
b0 D
bx C
bx B
xA
x@
bx ?
bx >
bx =
bx <
bx ;
bx :
b0 9
b0 8
b0 7
b0 6
bx 5
bx 4
bx 3
b0 2
b0 1
b0 0
b0 /
bx .
bx -
0,
0+
0*
0)
0(
0'
0&
0%
x$
x#
z"
z!
$end
#10000000
b0 .
b0 3
b0 :
b0 ?
b0 !"
b0 -
b0 Q
b0 X
b0 c
b0 ""
1+
#20000000
b0 5
b0 <
b0 >
b0 C
b0 J
b0 4
b0 ;
b0 =
b0 B
b0 O
b0 S
b0 Z
b0 b
b0 f
b0 s
b0 R
b0 Y
b0 a
b0 e
b0 }
0+
1,
#30000000
1+
#40000000
b111111x1 z
bx0xxxx p
b111111x1 w
bx0xxxx m
b11111101 u
b11111111 x
b1 k
b11101110 n
b11111101 /
b11111101 6
b11111101 D
b11111101 M
b11111101 T
b11111101 g
b11111101 {
b11111101 &"
b11111111 0
b11111111 7
b11111111 E
b11111111 N
b11111111 U
b11111111 h
b11111111 |
b11111111 %"
b1 1
b1 8
b1 F
b1 H
b1 V
b1 i
b1 q
b1 $"
b11101110 2
b11101110 9
b11101110 G
b11101110 I
b11101110 W
b11101110 j
b11101110 r
b11101110 #"
1%
1&
1'
1(
1)
0+
0,
1*
#50000000
0@
1+
#60000000
bx `
bx ]
b111111x1 [
bx0xxxx ^
b111111x1 R
b111111x1 Y
b111111x1 a
b111111x1 e
b111111x1 }
bx0xxxx S
bx0xxxx Z
bx0xxxx b
bx0xxxx f
bx0xxxx s
0P
b11111101 4
b11111101 ;
b11111101 =
b11111101 B
b11111101 O
0K
b1 5
b1 <
b1 >
b1 C
b1 J
0+
1,
#70000000
bx -
bx Q
bx X
bx c
bx ""
1@
b1 .
b1 3
b1 :
b1 ?
b1 !"
1+
#80000000
0+
0,
0*
#90000000
0@
b11111101 .
b11111101 3
b11111101 :
b11111101 ?
b11111101 !"
1+
#100000000
1K
b11101110 5
b11101110 <
b11101110 >
b11101110 C
b11101110 J
1P
b11111111 4
b11111111 ;
b11111111 =
b11111111 B
b11111111 O
0+
1,
#110000000
1@
b11101110 .
b11101110 3
b11101110 :
b11101110 ?
b11101110 !"
1+
#120000000
bx0 z
bx0xx1x p
bx0 w
bx0xx1x m
b11111110 u
b0 x
b10 k
b11101111 n
b11111110 /
b11111110 6
b11111110 D
b11111110 M
b11111110 T
b11111110 g
b11111110 {
b11111110 &"
b0 0
b0 7
b0 E
b0 N
b0 U
b0 h
b0 |
b0 %"
b10 1
b10 8
b10 F
b10 H
b10 V
b10 i
b10 q
b10 $"
b11101111 2
b11101111 9
b11101111 G
b11101111 I
b11101111 W
b11101111 j
b11101111 r
b11101111 #"
0+
0,
1*
#130000000
0@
b11111111 .
b11111111 3
b11111111 :
b11111111 ?
b11111111 !"
1+
#140000000
bx0 [
bx0xx1x ^
bx0 R
bx0 Y
bx0 a
bx0 e
bx0 }
bx0xx1x S
bx0xx1x Z
bx0xx1x b
bx0xx1x f
bx0xx1x s
0P
b11111110 4
b11111110 ;
b11111110 =
b11111110 B
b11111110 O
0K
b10 5
b10 <
b10 >
b10 C
b10 J
0+
1,
#150000000
1@
b10 .
b10 3
b10 :
b10 ?
b10 !"
1+
#160000000
0+
0,
0*
#170000000
0@
b11111110 .
b11111110 3
b11111110 :
b11111110 ?
b11111110 !"
1+
#180000000
1K
b11101111 5
b11101111 <
b11101111 >
b11101111 C
b11101111 J
1P
b0 4
b0 ;
b0 =
b0 B
b0 O
0+
1,
#190000000
1@
b11101111 .
b11101111 3
b11101111 :
b11101111 ?
b11101111 !"
1+
#200000000
bx1 z
bx00xx p
bx1 w
bx00xx m
b11111111 u
b1 x
b11 k
b11110000 n
b11111111 /
b11111111 6
b11111111 D
b11111111 M
b11111111 T
b11111111 g
b11111111 {
b11111111 &"
b1 0
b1 7
b1 E
b1 N
b1 U
b1 h
b1 |
b1 %"
b11 1
b11 8
b11 F
b11 H
b11 V
b11 i
b11 q
b11 $"
b11110000 2
b11110000 9
b11110000 G
b11110000 I
b11110000 W
b11110000 j
b11110000 r
b11110000 #"
0+
0,
1*
#210000000
0@
b0 .
b0 3
b0 :
b0 ?
b0 !"
1+
#220000000
bx1 [
bx00xx ^
bx1 R
bx1 Y
bx1 a
bx1 e
bx1 }
bx00xx S
bx00xx Z
bx00xx b
bx00xx f
bx00xx s
0P
b11111111 4
b11111111 ;
b11111111 =
b11111111 B
b11111111 O
0K
b11 5
b11 <
b11 >
b11 C
b11 J
0+
1,
#230000000
1@
b11 .
b11 3
b11 :
b11 ?
b11 !"
1+
#240000000
0+
0,
0*
#250000000
0@
b11111111 .
b11111111 3
b11111111 :
b11111111 ?
b11111111 !"
1+
#260000000
1K
b11110000 5
b11110000 <
b11110000 >
b11110000 C
b11110000 J
1P
b1 4
b1 ;
b1 =
b1 B
b1 O
0+
1,
#270000000
1@
b11110000 .
b11110000 3
b11110000 :
b11110000 ?
b11110000 !"
1+
